Workbook

Sheet Sheet1
A1: Unnamed: 0.1 | B1: Column 1 | C1: EDIH Title | D1: Description (indexed field) | E1: Country | F1: Contact name | G1: Contact Location | H1: EDIH/SoE | I1: Website | J1: Formatted sectors | K1: Formatted services | L1: Formatted technologies | M1: Unnamed: 0
A2: 1 | B2: 5 | C2: EDIH for DATA-BASED INNOVATION FOR CIRCULAR ECONOMY, OPERATIONS & SUSTAINABILITY | D2: The regional Data2Sustain EDIH consortium is a unique partnership approach across the NUTS II Northern and Western region. The consortium combines the core competences of the higher education institutes (HEI), with the innovation and business acumen of the complementary EDIH partners. This unique partnership structure demonstrates a shared management approach between researchers, technology providers, policy makers, innovation practitioners and business support agencies. The partnership structure encompasses 4 Technological Competence Centres, 3 Business support organisations, with 4 of the partners havin a local, or regional, planning, economic development, and investment remit, as well as European networked partner with extensive experience in digital innovation in public organisations. Data2Sustain is a coordinated group of organisations with complementary expertise, with a not-for-profit objective. It will support SMEs, as well as the public sector. It has a focus on circular economy, operations & sustainability areas, utilising AI, HPC and Cybersecurity technological competence, with particular emphasis of data/data analytics driven innovation and regard to energy consumption and low carbon emissions. We have jointly developed a comprehensive service programme to increase the transformation capacity and speed of SMEs/POs in the region, nationally and in Europe with regard to advanced digital innovations and skills development. The partnership has a comprehensive physical presence across the most economically challenged region of the state, with a well-established record of successfully engaging with target groups. Our ambition is to: ‘BE A LEADING EDIH IN THE PROVISION OF DIGITALISATION SERVICES IN THE AREA OF CIRCULAR ECONOMY, OPERATIONS & SUSTAINABILITY, BASED ON DATA AND DATA ANALYTICS DRIVEN INNOVATION APPROACHES HELPING TO CREATE SMARTER, GREENER, MORE SUSTAINABLE PROCESSES, SYSTEMS, PRODUCTS, SERVICES AND BUSINESS MODELS’ | E2: Ireland | F2: Mike Conroy | G2: ATU Sligo, Sligo, Co. Sligo, F91YW50, Ireland | H2: Seal of Excellence | I2: http://data2sustain.ie | J2: food and beverages, telecommunications, manufacturing and processing, construction assembly, travel and tourism, smart city, cultural and creative economy, life sciences | K2: field trial, prototyping, circular economy, sme business development, knowledge transfer, regional development, sme business development, ecosystem building | L2: artificial intelligence decision support, big data, high performance computing, cyberphysical systems, locationbased applications, communication network
A3: 2 | B3: 6 | C3: InnovTourism DIH - Gateway for Tourism innovation & digitalization, strengthening the sector ecosystem and enabling technology adoption in the industry | D3: InnovTourism DIH was designed to act as a key reference within the Portuguese and European digital innovation ecosystem, supporting SMEs, Start-ups, and PA in the sector to strive for their digital transformation processes, thus directly contributing to the Digital Europe Programme strategy of bringing digital technology to businesses, citizens and public administration. The HUB consists of a not-for-profit one-stop shop offering strategic services and tools aimed at increasing organizations digitalization, sustainability, competitiveness, production, and commercialization of products or services. A tourism industry-dedicated innovation HUB in Portugal is the ideal opportunity to generate regional, national, and European-level digital solutions through technological experimentation, finance and business advising, training, and skills development, supporting organizations developing inexistent solutions, in full alignment with the European Digital Innovation HUB spirit.The HUB action will strategically cover specific technological domains like Artificial Intelligence (AI), IoT, Biometrics, Virtual Assistants, Medium and Advances Digital skills, Gamification, AR/VR, Cloud Computing, Data Analytics, Predictable Modelling, Geolocation, Blockchain, and Cybersecurity. These topics will stand as a reference within the HUB services InnovTourism DIH is a non-profit, public-private cooperation between ten entities, coordinated by NEST Tourism Innovation Center Portugal (Cluster), followed by UniNova (Technology Interface Center), IPLeiria - Instituto Politécnico de Leiria (Entrepreneurship Knowledge Center), Algarve STP (Technology Developer), Beta-i (Accelerator), Turismo de Portugal (Tourism National Promoter), ACIFCCIM - Associação Industrial e Comercial do Funchal & Camara de Comércio e Indústria da Madeira, TTC "The Tomorrow Company" (Technology Developers), FI Group and Deloitte (Consultants). | E3: Portugal | F3: Manuel Trindade | G3: Praça do Municipio, 6200-000 Covihã, Portugal | H3: Seal of Excellence | J3: food and beverages, smart city, travel and tourism, transport mobility | K3: circular economy, ecosystem building, innovation management, knowledge transfer, sme business development, sme support, technology transfer, technological innovation, vocational training | L3: artificial intelligence decision support, big data, blockchain and distributed ledger technology dlt, cloud services, communication network, cybersecurity, digital twins, internet of things, internet services applications, virtual reality
A4: 3 | B4: 7 | C4: ANDALUSIAN DIGITAL INNOVATION HUB IN ARTIFICIAL INTELLIGENCE AND ROBOTICS | D4: The main objective of AIR-Andalusia is to set up and guarantee the correct operativity of a regional node for the European Digital Innovation Hubs in Andalusia (Spain). Located in the south of the Iberian Peninsula, Andalusia is the most populated Autonomous Community and the second largest in Spain; being an outermost region of Europe. AIR-Andalusia is conceived as a supporting tool to foster the digital transformation of the region, focused on applied Artificial Intelligence and Robotics for (a) SMEs and small mid-caps and (b) public sector organisation, as varied a sectoral coverage as possible. AIRA aims to improve entities’ efficiency and competitiveness, providing them with access to different digitalization services focused on improving business processes, products or services. The services list includes different offers of support covering the whole life cycle of the new product/service development, either to solve technical gaps (‘Test before Invest’ and ‘Training’), to foster synergies with other relevant stakeholders for the service/product development (‘Ecosystem’); options to fund potential R&D or investment projects as the last step for the scale-up of the tested solutions (‘Find Investment’). Therefore, the consortium expects to cover all the potential needs of the entities, prioritising SMEs, to help them reach market. Up to 1.624 complete services are expected to be given during the 3 years period to about 325 entities, including SMEs, start-ups and mid-caps, and public entities. Finally, mobilising new investment in the region to reach the digital transformation. The consortium (20 beneficiaries and 4 Affiliated Entities) is multisectoral and wide enough to cover the great diversity of application sectors of AI and robotics, and the territorial distribution in this extensive region, including representation of Research and Technology entities, Technological companies, Technological Parks and Entrepreneurial associations. | E4: Spain | F4: Enrique Herrera Viedma | G4: Cuesta del hospicio sn, 18071 Granada Granada, Spain | H4: Seal of Excellence | I4: https://www.airandalusia.es/es/home-espanol/ | J4: defence, education, energy, environment, health care, manufacturing and processing, personal services, public administration, security, smart city, telecommunications, transport mobility | K4: innovation management, knowledge transfer, prototyping, technological innovation, sme support, vocational training, technology transfer | L4: artificial intelligence decision support, robotics, big data, digital twins, quantum technologies computingcommunication, simulation engineering and modelling
A5: =A4+1 -> 4 | B5: 8 | C5: NASK – National Research Institute | D5: Cybersecurity and user protection – our key activities involve ensuring security online. Responding to network security violations occurring in Poland and coordinating corrective actions is the responsibility of the Centre for Cybersecurity. The Center for Standardization and Certification of NASK-PIB, an organizational unit included in the internal Organizational Regulations within NASK acts as an accredited Certification Body. The center certifies products in the field of IT security (cybersecurity). With the enactment of the Act on the national cybersecurity systems, NASK was given the important role of serving as one of three nation-wide CSIRTs. The NASK CSIRT receives and analyses reports, takes actions and coordinates responses to incidents occurring in Polish civilian cyberspace reported by key service operators, digital service providers, local authorities and individuals. It also responds to incidents involving the uploading of content which is illegal or poses a hazard to children; as well as monitoring online threats and the level of cybersecurity in individual sectors and the entire country. Keywords: Cybersecurity, Certification | E5: Poland | F5: Magda Druzd | G5: Kolska 12 st, 01-045 Warsaw, Poland | H5: DIH | I5: https://en.nask.pl/ | J5: defence, telecommunications, security | K5: knowledge transfer, regional development, sme support | L5: cloud services, cyberphysical systems, cybersecurity, internet of things
A6: =A5+1 -> 5 | B6: 9 | C6: Pôle SCS | D6: SCS (Secured Communicating Solutions) cluster (www.pole-scs.org), is based in the Provence-Alpes-Côte d’Azur region, in France, and gathers 300 members, including companies (and 70% of SMEs), research centres and educational institutions in the fields of microelectronics, IoT, Big Data, Artificial Intelligence and Digital Security. As a non-profit organisation with the status of "French Competitiveness cluster" recognised at national level, the aim of SCS cluster is to promote the development of competitive R&D projects between all these players with the support of local communities, in order to design and develop new solutions targeting high-growth markets such as smart cities, smart homes and smart buildings, smart grids, Industry x.0, or e-health. It also aims to contribute to the creation of an appropriate ecosystem for the overall regional digital and deeptech landscape, especially through the development of SMEs. The cluster represents 60 000 jobs in these fields, 26 multinational companies, 1200 researchers in the public sector and 18 educational institutions training 1500 engineers per year. Partner in the European Digital Innovation Hub Move2Digital Keywords: Open innovation, networking, Deeptech, digital technologies, IoT, AI, cybersecurity, microelectronics, electronics, optics, photonics | E6: France | F6: Marielle Campanella | G6: Place borde, 13790 Rousset, France | H6: DIH | I6: https://www.pole-scs.org/ | J6: defence, energy, health care, telecommunications, security, smart city, transport mobility | K6: innovation management, knowledge transfer, prototyping, regional development, smart specialisation strategies, sme business development, sme support, technological innovation | L6: artificial intelligence decision support, big data, cybersecurity, internet of things, micro and nanoelectronics, optoelectronics, photonics, semiconductors and nanotechnology, sensors vision processing systems, simulation engineering and modelling
A7: =A6+1 -> 6 | B7: 10 | C7: Cybersecurity Innovation Hub | D7: CIH will significantly support digital transformation and application of innovation in SMEs and public administration by building a coordinated and effective ecosystem comprising top research institutions with the necessary know-how and infrastructure, specialized business clusters, professional organizations, and public authorities. This robust ecosystem will provide its beneficiaries with access to education and information on cybersecurity trends and best practices, to expert advice and state-of-the-art infrastructures to verify the suitability and security of innovative solutions under consideration and increase the availability of funds to invest in innovation. CIH will also function as a platform for cooperation and information sharing between entities in the cybersecurity market, both at the level of Czechia and the EU. This will increase the efficiency and competitiveness of the EU cybersecurity industry, the security of IT infrastructures and the strength of the EU economy. CIH draws on partnerships and participation in international networks and builds on the success of Czech research and industry. CIH covers cybersecurity on the horizontal from various points of view (technical, legal, economic, social etc.), on the vertical CIH operates at all levels - it plays an important role in building the legislative environment, in research, commercialization and implementation of technologies, and in awareness raising and education. CIH also has links to standardization and certification that shape the cybersecurity market. This holistic approach and the ability to thoroughly map the ecosystem make CIH an attractive partner for international cooperation. This is also confirmed by its participation in 3 EU pilot research projects (Sparta, CyberSec4Europe and Concordia), cooperation with the EU and international organizations (ENISA, Europol, UN, NIST, etc.), and involvement in professional initiatives (e.g. REWIRE - capacity building in cybersecurity in the EU). | E7: Czechia | F7: Tereza Samanova | G7: Šumavská 416/15, 602 00 Brno, Czechia | H7: EDIH | I7: https://www.cybersecurityhub.cz/ | J7: defence, education, energy, environment, financial, health care, life sciences, manufacturing and processing, metal working and industrial production, personal services, public administration, retail, wholesale or distribution, security, smart city, space, telecommunications, transport mobility, transport sector, travel and tourism | K7: ecosystem building, innovation management, finance, knowledge transfer, prototyping, public sector innovation, sme business development, sme support, technological innovation, technology transfer, vocational training | L7: artificial intelligence decision support, big data, cloud services, communication network, cyberphysical systems, cybersecurity, high performance computing, internet of things, internet services applications, software architectures
A8: =A7+1 -> 7 | B8: 11 | C8: EDIH Czech Technical University in Prague | D8: The EDIH CTU represents a major European Digital Innovation Hub in the Czech Republic in the field of Artificial Intelligence (AI) and Machine Learning (ML) transferring trustworthy solutions and services to the industry, health, transportation and energy sectors. The EDIH CTU, with its vision "Inspire & Make the Czech AI-driven Industry", aims to become the innovation and technology leader in providing professional AI/ML services for the local SMEs, small mid-caps and public sector organizations with respect to their digital and green transformation. The strong consortium partners representing academia, the business sector and key associations of enterprises in the Czech Republic provide sufficient know-how, expertise and state-of-the-art experimental facilities to serve the needs of the public and private sectors at the national and also international levels. The major focus is on promoting digital transformation adoption, providing high-quality services, education and knowledge sharing, pursuing ecosystem development, and establishing strong inter-EDIH collaboration. The consortium builds upon already existing partnerships in AI and manufacturing enabling best practice sharing, expertise exchange, and joint activities seeking far-reaching synergies thus strengthening the far-reaching impacts of the European network of EDIHs. | E8: Czechia | F8: Barbora Zochova | G8: Jugoslavskych partyzanu 1580/3, 160 00 Praha, Czechia | H8: EDIH | I8: https://www.edihctu.eu | J8: telecommunications, automotive, construction assembly, education, electricity, energy, environment, health care, manufacturing and processing, metal working and industrial production, nuclear, public administration, smart city, space | K8: technology transfer, technological innovation, sme support, smart specialisation strategies, public sector innovation, circular economy, field trial, innovation management, prototyping, vocational training | L8: artificial intelligence decision support, bi tools, gamification, software architectures, sensors vision processing systems, robotics, human computer interaction, internet of things, internet services applications
A9: =A8+1 -> 8 | B9: 12 | C9: Digital Innovation Hub for a Smarter, Safer and more Sustainable Society (DIH4Society) | D9: News: launched the call for selecting the SMEs who will benefit from the services. Details & info are available: https://dih4society.ro/apel-imm/ Accelerating digital green transformation and innovation uptake across the economy and society is at the forefront of Europe’s growth agenda. Digital Innovation Hubs (DIHs) are one of the pillars to uphold this process and will help to consider the geographical (regional) dimension and thematic context to boost SME growth, citizen centered governance, jobs and investment. The COVID19 crisis has demonstrated the absolute necessity of having strong European digital ecosystems as key enablers to avoid disruption in value-chains. However, digitalization and digital transformation can only be efficient if digital ecosystems are strongly interlinked with their applied market sectors. Due to inertia and/or legacy, the manufacturing, public administration and health sectors are among the most challenging ones. The project Digital Innovation Hub for Society for a Smarter, Safer and more Sustainable Society comes to upscale the services that DIH4Society can deliver in the North-West Region of Romania and aims at fully integrating our initiative into the European network of hubs. The project focuses on two technological pillars, cybersecurity and smart robotics, while also building advanced digital competencies for digitalization and green digital transformation. Upon finalization, the project will have a profound, transformative impact on a regional level through the digital progression of 70 key stakeholders, public administration and health providers, and more than 400 SMEs from smart specialization sectors. DIH4Society will provide a European solution to a European challenge and will bring or embed digitalization in the practices of many organizations. In the long run the project will inspire a new generation of early adopters of technologies, new entrepreneurial initiatives of visionary companies and organizations that use cutting edge technologies at the core of their business models and will build the foundation for a citizen centered public service delivery. | E9: Romania | F9: Andrei KELEMEN | G9: Str. Dorobantilor 57A, First Floor, 400609 Cluj-Napoca, Romania | H9: EDIH | I9: https://dih4society.ro/ | J9: manufacturing and processing, public administration, health care, smart city, communityled local development, education, energy | K9: ecosystem building, field trial, finance, innovation management, knowledge transfer, prototyping, public sector innovation, regional development, smart specialisation strategies, sme business development, sme support, technological innovation, technology transfer, vocational training | L9: cybersecurity, robotics, artificial intelligence decision support
A10: =A9+1 -> 9 | B10: 13 | C10: Digital Innovation Hub of the Galician Industry | D10: Galicia is the 6º Spanish region least digitalized, according to the DiGiX that assesses the factors that enable to fully leverage ICTs for increased competitiveness and well-being. Being 99,92% of Galician companies SMEs, there is a clear need to address digitalization at this scale. Furthermore, manufacture is not only a critical sector for the Digital Europe Programme, but it also represents almost 15% of the Galician economy. European digitalization of SMEs goes necessarily through the digitalization of the Galicia manufacturing SMEs. DIHGIGAL's goal is to boost the digital transformation of all industry focusing on SMEs and mid-caps needs. This will be achieved by the diverse composition of its consortium: *3 leading manufacturing sectors (automotive, naval and food) represented by their clusters (CEAGA, ACLUNAGA & CLUSAGA) bringing together not only their companies (20,000M€ turnover and 50,000 employees) but also their technology centres along with a cross-sectorial ecosystem (Galicia Digital) which opens the EDIH to whole industrial sector. *4 leading competence centres combining the best capacities in HPC and AI represented by CESGA-Supercomputing Centre, ITG and Universities of Vigo and Coruña (which chairs the Spanish Association for AI) along with the private supply through the ICT cluster. *3 complementary agents (FEUGA, KPMG & Inovalabs) to provide service to the entire digital ecosystem. All of them are crucial to implement specialized actions and to extend the scope and impact of the project. In this sense, DIHGIGAL is part of a broader vision aligned with policies at regional (RIS3), national, and European (2030 Digital Compass, Green Deal, and White Paper on AI) level. In terms of the foreseeable impact, over 800 SMEs, mid-caps and public entities are expected to benefit directly from the project and the collaboration with other EDIHs. This is DIHGIGAL commitment to enhance the twin transition in Galicia and, hence, the EU. | E10: Spain | F10: Josefina Alonso Nocelo | G10: Avda. Citroën, 3 y 5 – Edificio Zona Franca 1ª Planta, 36210 Vigo Pontevedra, Spain | H10: Seal of Excellence | I10: https://dihgigal.com | J10: manufacturing and processing, automotive, transport mobility, food and beverages, maritime, retail, wholesale or distribution, textiles | K10: sme support, ecosystem building, finance, technological innovation, circular economy, innovation management, vocational training, technology transfer, smart specialisation strategies, regional development, public sector innovation | L10: artificial intelligence decision support, high performance computing, big data, cybersecurity, internet of things, mobility, quantum technologies computingcommunication, sensors vision processing systems
A11: =A10+1 -> 10 | B11: 14 | C11: Digital Innovation Hub for Nouvelle-Aquitaine Manufacturing Industry Community | D11: Led by a consortium of 13 partners, DIHNAMIC aims to give access to AI-based digital technologies, advanced robotics, digital twinning and intelligent systems. Granting access to these resources is expected to accelerate and guide the green, digital and sustainable transition of 116 innovative manufacturing companies and 8 public authorities from the French Nouvelle-Aquitaine region. With a total number of 600 services delivered over the course 3 years, DIHNAMIC will encourage and support the development of a digitised, resilient and resource-efficient industry in line with trustworthy AI concepts. DIHNAMIC will contribute to the objectives laid-out in policies such as the New Industrial Strategy for Europe, the Digital Europe Programme”, "Europe fit for the Digital Age Strategy”, or the “European Green Deal”. The services offered are designed to foster the uptake of trustworthy AI, in response to the industry's need to adapt to current economic, ecological and societal challenges, while considering applied ethical and environmental aspects in their innovation and digitalisation process. AI-based service follow the recommendations from the “European Trustworthy AI strategy” Links and partnerships will be established with other EDIHs and research centres active in AI, HPC and Cybersecurity. DIHNAMIC will act as a transmission belt, transmitting feedbacks from the regional ecosystem to European authorities while contributing to the implementation of European policies and strategies. DIHNAMIC will also facilitate the access of regional companies to finance, helping companies to raise a total of 2 million euros in additional investment over the course of 3 years. To enable a rapid start of the project, DIHNAMIC has already established a customer journey and developed dedicated delivery channels to favour cross-learning and impactful service delivery. | E11: France | F11: Véronique Desbleds | G11: 6 allee du doyen georges brus, 33600 Pessac, France | H11: EDIH | I11: https://www.dihnamic.eu | J11: manufacturing and processing, aeronautics, agricultural biotechnology and food biotechnology, health care, energy, defence, environment, transport sector | K11: technological innovation, prototyping, public sector innovation, ecosystem building, sme support | L11: artificial intelligence decision support, big data, digital twins, high performance computing, human computer interaction, internet of things, robotics, virtual reality, additive manufacturing, cybersecurity, logistics
A12: =A11+1 -> 11 | B12: 15 | C12: EDIH CASSOVIUM | D12: Mission of the project EDIH CASSOVIUM (EDCASS) is to support reinforcement of European critical digital technologies and their best use in green digital transformation of industrial and public ecosystems in the region of the Eastern Slovakia Region (ESK-REG). Consortium of three top-research and innovation institutions in ESK-REG – two internationally recognised universities Technical University in Košice (coordinator) and Pavol Jozef Šafárik University in Košice, and a highly recognised ICT cluster Košice IT Valley. ESK-REG consisting of Košice Self-governing Region and Prešov Self-governing Region, which in European context are classified as “less developing regions” has low level of innovation score and use of digital services, also low an unemployment rate (of 8.2 %) and level of average wages. Therefore, it is important that EDCASS ensures its digital transformation services are easily accessible to all SMEs (95+ % of all companies in ESK-REG) and public institutions. The key goal of EDCASS is to provide one-stop-shop support for four categories of EDIH services with an adequate, knowledge-based, and technically high-quality range of information technologies guaranteed by the ecosystem of the consortium partners. The consortium covers a wide range of multi-sectors and multi-dimensional ICT areas, which fall within research and educational competencies of all partners. EDCASS platform is based on three basic pillars: 1) Artificial Intelligence and Robotics; 2) Industry 4.0/5.0 concepts, application and implementation; 3) Cyber security solutions for commercial and public subjects. In line with its mission, these services and technologies are and will be supported by active links to European DIH, EDIH networks and other European networks (EEN, Startup Europe) and bilateral collaboration with suitable partner research and innovation institutions. | E12: Slovakia | F12: Miroslav Michalko | G12: Letná 1/9, 042 00 Košice, Slovakia | H12: EDIH | I12: https://www.edihcassovium.sk | J12: manufacturing and processing, smart city, public administration, energy, transport mobility, telecommunications, education, aeronautics, construction assembly, cultural and creative economy, metal working and industrial production, travel and tourism, mining and extraction | K12: prototyping, innovation management, ecosystem building, sme business development, technology transfer, technological innovation, public sector innovation, regional development, smart specialisation strategies, vocational training, finance, circular economy | L12: artificial intelligence decision support, cybersecurity, robotics, big data, simulation engineering and modelling, software architectures, internet of things, cyberphysical systems, cloud services, communication network, additive manufacturing, digital twins, virtual reality, blockchain and distributed ledger technology dlt, micro and nanoelectronics, optoelectronics, gamification, high performance computing
A13: =A12+1 -> 12 | B13: 16 | C13: EDIH Lombardia | D13: EDIH L - M.I.A. Lombardia The mission of EDIH Lombardia (EDIH L) is to lead and implement the digital and sustainable twin transition of Lombardy’s manufacturing industry through a comprehensive portfolio of services provided by its partners. Recognized as a EDIH and awarded the "Seal of Excellence", EDIH Lombardia plays a key role in driving digital and sustainable transformation in Lombardy, one of Europe’s most productive regions. Recently renamed as Manufacturing Innovation Alliance (M.I.A.) Lombardia, the organization is a consortium of 12 partners dedicated to supporting manufacturing companies in their digitalization efforts, in alignment with European and national industrial policies. The consortium includes 1 Competence Center, 1 Digital Innovation Hub (both listed in the JRC catalogue), 4 Technology Clusters, 3 Business Associations, 1 Financial Institution, 2 EIT Nodes. M.I.A. Lombardia aims to support digitalization and sustainability in the manufacturing sector, with a particular focus on SMEs. It offers a broad range of tailored services, including consultancy, training, and access to funding, helping companies adopt innovative technologies, enhance competitiveness, and drive sustainable transformation. Specific Objectives Supporting digital and sustainable transformation:M.I.A. Lombardia guides manufacturing companies through their digitalization journey, promoting the adoption of advanced technologies to improve efficiency and sustainability. This includes Industry 4.0 solutions and greener, more digitalized processes. Providing personalized services:The hub offers tailored services such as technical consultancy, training, and audits, adapting to each company's specific needs. This approach enables businesses to tackle digitalization challenges with the right tools and scalable solutions based on their digital maturity level. Leveraging NRRP funds and state incentives:Through PNRR financing and various incentives, M.I.A. Lombardia provides companies with financial resources to support the adoption of innovative technologies. These funds are allocated based on company size, with some incentives covering up to 100% of costs for micro and small enterprises. Promoting advanced technological skills:M.I.A. Lombardia organizes awareness-raising and training initiatives to help companies understand and implement new technologies. By offering testing programs and prototype development, businesses can evaluate technological solutions before large-scale investments, reducing risks and accelerating digital transformation. As part of M.I.A. Lombardia, MADE coordinates the “EDIH Manufacturing Network – EDIH4MANU”, an open, informal collaboration network of 25 EDIH candidates from 15 EU countries. This network aims to connect Europe’s most advanced manufacturing regions, share specializations, best practices, competencies, and services, and promote the digital transition of European industry. | E13: Italy | F13: Carlo Ongini | G13: Piazza Leonardo Da Vinci 32, 20133 Milano MI, Italy | H13: Seal of Excellence | I13: https://www.mialombardia.it/ | J13: manufacturing and processing, communityled local development, life sciences, textiles, aeronautics, education, metal working and industrial production, automotive | K13: sme support, technology transfer, vocational training, field trial, prototyping, regional development, ecosystem building, innovation management, circular economy, technological innovation | L13: artificial intelligence decision support, human computer interaction, robotics, digital twins, cybersecurity, big data, additive manufacturing, internet of things, logistics, simulation engineering and modelling, virtual reality
A14: =A13+1 -> 13 | B14: 17 | C14: EDIH MADRID REGION | D14: Madrid is a Spanish region covering only 1.6% (8,030 km2) of the country’s area but it generates 19,3% of Gross Domestic Product (GDP) and where 14,2% (6.7 million) of the population of the Country live. Madrid Region has one of the major enterprise’s densities of all country, 85.8 companies per 1,000 inhabitants and it concentrates near 16,2% of all companies in Spain. In total, there are 552,027 enterprises in the Region . This makes Madrid Region a Business decision Centre. The EDIH MADRID REGION is created with the aim of being the reference Centre to improve the digitization of both public sector and small and medium-sized companies in Madrid Region. To achieve this ambitious goal, EDIH MADRID REGION is made up of a powerful consortium of 11 partners. EDIH MADRID REGION is led (coordinated) and co-financed by the regional government of Madrid. One of the members of the consortium is the Fundación para el Conocimiento madri+d (Fmi+d), which is the coordinator of the Madrid node of the European Enterprise Network (EEN). In this way, it is ensured that EDIH MADRID REGION will offer a continuous service with EEN and Startup Europe. Among the EDIH MADRID REGION partners there are several partners who have a deep understanding of the needs of the entities to which the services to be provided by the EDIH are addressed. EDIH MADRID REGION partners include several partners with extensive experience in developing solutions based on the key digital technologies of the Digital Europe programme. Based on the key sectors identified in the previous strategy, the regional policies in various areas, the priorities of the Digital Europe program and the experience of the partners of the EDIH MADRID REGION consortium, it has been decided to prioritize the following economic sectors to give their digitization support services: o SMEs in the services sector o SMEs in the industrial sector: Industry 4.0 o Regional and municipal public administration o The area of mobility | E14: Spain | F14: Pedro Jesus Rodriguez | G14: Calle del Maestro Ángel Llorca, 6, 28003 Madrid Madrid, Spain | H14: EDIH | J14: manufacturing and processing, personal services, public administration, education, transport mobility, construction assembly, aeronautics, agricultural biotechnology and food biotechnology, transport sector, travel and tourism | K14: knowledge transfer, innovation management, prototyping, public sector innovation, sme support, technological innovation, technology transfer | L14: artificial intelligence decision support, cybersecurity, high performance computing, blockchain and distributed ledger technology dlt, robotics, simulation engineering and modelling, mobility, cloud services, locationbased applications, internet of things
A15: =A14+1 -> 14 | B15: 18 | C15: European Digital Innovation Hub for employee-centered digital transformation in South Westphalia | D15: The planned EDIH is located in the German region of South Westphalia. South Westphalia is an industrial region with a strong focus on small and medium-sized enterprises (SMEs), with more than 150 so-called “hidden champions”, i.e. those often little-known small and medium-sized enterprises that are among the European and world market leaders in niche markets. The major industrial sectors of metal production and processing as well as mechanical engineering generate 75 % of total sales in the industrial sector each year, accounting for about two-thirds of total industrial employment. South Westphalia is therefore not only the third strongest region in Germany and by far the strongest industrial region in North Rhine-Westphalia (most populous federal state in Germany), but also one of the oldest industrial regions in Europe. However, the strategic orientation of EU policies and the twin objectives of making Europe greener and more digital poses challenges for the rather traditional “old industry” within South Westphalia. The focus must therefore be on providing the best possible support for SMEs within South Westphalia in overcoming these challenges. For this reason, establishing an EDIH with a strong European orientation is of particular benefit to the South Westphalian economy with its high export quota. The economic success of SMEs in South Westphalia is based on the expertise of their employees, which has grown over decades. The EDIH SWF will provide a set of services and infrastructures to support SMEs in how this product-specific expertise of human specialists and executives can be complemented by the adoption and development of in-depth, socio-informatic digitization competencies in the design of human-centered artificial intelligence, employee-based cyber-security as well as socio-technical assistance systems. The EDIH will support SMEs during the transformation process in cooperation with the social partners to maintain innovative strength in the long term. | E15: Germany | F15: Thomas Ludwig | G15: Adolf-Reichwein-Strasse 2a, 57076 Siegen, Germany | H15: EDIH | J15: manufacturing and processing, metal working and industrial production, automotive, construction assembly, public administration, smart city, health care | K15: prototyping, sme support, field trial, innovation management, knowledge transfer, circular economy, technological innovation, technology transfer, public sector innovation | L15: cyberphysical systems, human computer interaction, additive manufacturing, internet of things, digital twins, virtual reality, artificial intelligence decision support, gamification, internet services applications, laserbased manufacturing and materials processing, robotics, new technologies for audiovisual sector media, cybersecurity, mobility
A16: =A15+1 -> 15 | B16: 19 | C16: EDIH VILNIUS: accelerating green and digital transformation in Vilnius region | D16: Responding to the DIGITAL-2021-EDIH-01-INITIAL call, EDIH VILNIUS is submitting the proposal with a goal to enable the EDIH VILNIUS to effectively support the digital and green transformation of SMEs and public sector organisations in the Vilnius region. The specific objectives of the project directly correspond to the objectives of the call and are the following:(1) to ensure full integration of the EDIH VILNIUS into a common network of EDIHs in order to facilitate effective international cooperation and service provision as well as identify and cover the needs of Vilnius region SMEs and public sector organisations in a field of digital and green transformation by providing a full package of integrated services(2) to upgrade the capacity of the EDIH VILNIUS to ensure the proper provision of these services(3) to build networks between EDIH VILNIUS and other relevant organisations in Europe and worldwide in order to ensure sharing of capacities and knowledge, especially, in the fields of High Performance Computing, Artificial Intelligence, Cybersecurity, Advanced Digital Skills. Moreover, the project will directly contribute to the overall Digital Europe Programme objectives as EDIH VILNIUS will become a part of EDIHs network on the EU level and will help to cover a specific EU region (Vilnius region, Lithuania). EDIH VILNIUS is already a mature consortium which is deeply engaged in its activities. At the moment the consortium brings together digital technology expertise, with the specific focus on AI technologies, in different sectors as well as infrastructure needed to provide high quality services in the Vilnius region. Therefore, EDIH VILNIUS is able to ensure a successful implementation of the project and its objectives. The project will help members of EDIH VILNIUS to better combine their forces, infrastructure and competencies for a common goal - comprehensive digital and green transformation of Lithuanian industry, SMEs and public sector organisations. | E16: Lithuania | F16: Evelina Šalavėjienė | G16: Sauletekio al. 15, 10224 Vilnius Lithuania, Lithuania | H16: EDIH | I16: http://www.edih.lt | J16: manufacturing and processing, manufacturing and processing, education | K16: circular economy, sme support, technological innovation, technology transfer, sme business development, ecosystem building | L16: additive manufacturing, artificial intelligence decision support, cyberphysical systems, cybersecurity, digital twins, high performance computing, internet of things
A17: =A16+1 -> 16 | B17: 20 | C17: EDIH-DIGIMAT: Flexible Manufacturing Systems Using Artificial Intelligence | D17: EDIH-DIGIMAT’s vision is more digitalized, productive, and competitive manufacturing sector, with its workforce adapted to this trend. It wants to contribute to sustaining the importance of the manufacturing sector to the Czech GDP, employment level, and exports. To achieve its objectives, EDIH-DIGIMAT proposes a comprehensive, structured program for digitalization of manufacturing companies, starting by raising the awareness, continued education of the companies’ staff, providing advisory and consultancy services to the respective company management levels, through experimenting with the companies at the test rigs. EDIH-DIGIMAT’s consortium builds on a successful first operational DIH in the country – DIGIMAT. It consists of four partners: INTEMAC as a lead partner with its footprint in digital consultancy services, JIC with funding services and business consulting in general, Effectivity serving the industry on their productivity growth journey, and BUT as the largest technology university in the country with a wide spectrum of technical expertise and a wide network of industry partners. To elevate the services offered, the EDIH-DIGIMAT engaged multiple clusters and partner organizations, both domestically and abroad. The array of partners includes also technology providers, domestic as well as foreign EDIH candidates. This approach has been designed to ensure relevance of provided services in time, as well as to increase the depth and breadth of provided services. The EDIH-DIGIMAT is going to be backed by a robust governance model to ensure the proposed plan is going to be executed for the benefit of the targeted manufacturing sector, and the society at large. | E17: Czechia | F17: Veronika Vecerova | G17: Blanenska 1288/27, 664 34 Kurim, Czechia | H17: EDIH | I17: https://www.edih-digimat.cz/ | J17: manufacturing and processing, automotive, construction assembly, energy, environment, metal working and industrial production, polymers and plastics | K17: circular economy, ecosystem building, innovation management, knowledge transfer, prototyping, sme support, technological innovation, technology transfer, vocational training | L17: additive manufacturing, artificial intelligence decision support, digital twins, internet of things, cyberphysical systems, robotics, sensors vision processing systems
A18: =A17+1 -> 17 | B18: 21 | C18: Digital Hub Logistics Dortmund as European Digital Innovation Hub | D18: The aim of the Digital Hub Logistics Dortmund as EDIHDO is to increase the dissemination, acceptance and adoption of digital technologies and their successful application for the development of product, process and business model innovations by SMEs. To this end, EDIHDO offers support formats and services in the categories Test before Invest, Skills & Training, Investment Search Support and Innovation Ecosystem & Networking. EDIHDO is supported by Fraunhofer IML and TU Dortmund as competence centres, Digital Hub Management as orchestrator and finally TZNet, a subsidiary of the City of Dortmund, and WFG Kreis Unna, a subsidiary of the district of Unna, as multipliers. EDIHDO focuses on the application area of logistics, manufacturing and production. In the area of digitalisation, the technological focal points include artificial intelligence, high-performance computing, the Internet of Things, blockchain, sovereign data exchange and cyber-physical systems, based on the needs of companies in the region, the potential in the application area and the competences of the consortium partners. Since the successful use of digital technologies in innovative products, processes and business models requires above all the digital competences of the employees, EDIHDO also places a special focus on offers in the area of digital further qualification. In the area of cyber security, which also plays an important role in the acceptance and implementation of digital technologies, EDIHDO acts as an intermediary to the existing competence centres in the region. Further technology competences can be brought in through cross-border cooperation and exchange in the EDIH network. In this way, SMEs and SMEs in the region can be comprehensively supported in the digital transformation, the strengthening of competitiveness can be ensured and thus the regional economic competitiveness and future viability can be secured. | E18: Germany | F18: Maria Beck | G18: Emil-Figge-Straße 80, 44227 Dortmund, Germany | H18: EDIH | I18: https://edih-do.eu/en/ | J18: manufacturing and processing, metal working and industrial production, automotive, transport mobility, communityled local development, smart city, real estate, retail, wholesale or distribution, cultural and creative economy, personal services | K18: sme support, ecosystem building, innovation management, knowledge transfer, regional development, prototyping, vocational training, sme business development, technological innovation, technology transfer, field trial, finance, circular economy, smart specialisation strategies | L18: logistics, artificial intelligence decision support, big data, digital twins, internet of things, additive manufacturing, cyberphysical systems, robotics, blockchain and distributed ledger technology dlt, cloud services, cybersecurity, gamification
A19: =A18+1 -> 18 | B19: 22 | C19: Development of AI – ICT for Manufacturing EDIH in Latvia | D19: LDIH unites Latvia’s leading research and technology organizations that are well-positioned to deliver technological and expert services. Based on a field of specialization, key enabling technologies under this category are AI and robotic solutions for manufacturing and business process automation. An Applied AI Knowledge Centre will be established to create an environment for detailed internal and external business process research. The purpose of the AI Centre Lab will be to demonstrate and model for businesses the advantages of implementing AI solutions in production processes tailored to their business model. In terms of community impact, the centre aims to increase accessibility to digital guidance and infrastructure in a local perspective, making it a matchmaking platform for scientists and businesses. The centre will provide the virtual and physical infrastructure for events and content creation. On a larger scale, the foundation of the centre will serve as an entity that holds knowledge and executes national-level digital transformation. Furthermore, it will connect the local digital ecosystem to the European digital network community and tap into the global AI community. LDIH will facilitate awareness in municipalities of the benefits of digitalisation in sustainable development and work towards an improved business environment in regions. This will be achieved by sharing best practice cases on implementing measures to facilitate the uptake of digital technologies, consequently improving the business environment and providing training and courses for Latvian municipality employees to raise awareness regarding the opportunities and impact that digitalisation can bring to local communities as well as skills improvement to mainstream the use of e-governance tools. | E19: Latvia | F19: Ilze Raudina | G19: Skolas iela 11, Riga, LV-1010, Latvia | H19: EDIH | I19: https://dih.lv/lv | J19: manufacturing and processing, transport mobility, smart city, metal working and industrial production, food and beverages, energy, education, automotive, agricultural biotechnology and food biotechnology | K19: ecosystem building, regional development, sme business development, sme support, technological innovation, technology transfer, smart specialisation strategies | L19: artificial intelligence decision support, big data, cloud services, communication network, cybersecurity, digital twins, high performance computing, internet of things, internet services applications, mobility, quantum technologies computingcommunication, robotics, sensors vision processing systems, virtual reality
A20: =A19+1 -> 19 | B20: 23 | C20: EDIH Odense for deployment of collaborative robots (cobots) in many domains especially manufacturing and logistics | D20: Aim: The purpose of EDOcobot is to improve robot skills and increase the deployment of useful collaborative robots (cobots) in SMEs and small mid-caps and thereby support production in Denmark and Europe, supporting DIGITAL objectives. Method: We categorised end users according to their robot experience and general digital skills and have designed a set of services that cover the whole continuum. As experienced companies are already aware of many options and opportunities, our services focus particularly on beginner SMEs. Beginners are introduced to the variety of cobot systems and led to discover which would work best for them, how their factory needs to be reorganised for the cobot, and how this investment can be funded. “Robot-ready” SMEs are encouraged to deploy more cobots, also in other types of application, and to train more of their staff to operate and program cobots. “Innovator” SMEs are taught how to optimize the way they use cobots and are introduced to tech suppliers, while “Front-runners” are matched with tech developers (and perhaps research calls) so that their end-user challenge can contribute to the future direction of the tech. Expected results: All our customers develop a deeper understanding of cobots and how to use them to best advantage, increasing their hands-on digital skills. They also gain better knowledge of funding opportunities and interact with the wider robot ecosystem. More cobots are deployed in various industrial sectors, including those where robot penetration is traditionally low. Mitigation of the shortage of skilled labour, reduction in workplace injuries, more reliable product quality, less waste. Relevance to the call: Increasing the robot awareness and skills of “beginners” will have great impact on the overall digital skills of European SMEs. Improving European productivity will reduce our reliance on foreign supply chains. Cobots are an accelerating market, so the EDIH network needs a node with a pure cobot focus. | E20: Denmark | F20: Lars Kristensen | G20: Munkebjergvænget 1, 5230 Odense M, Denmark | H20: EDIH | J20: manufacturing and processing, public administration, metal working and industrial production | K20: innovation management, knowledge transfer, prototyping, sme support, technological innovation | L20: robotics, logistics, artificial intelligence decision support, mobility, sensors vision processing systems
A21: =A20+1 -> 20 | B21: 24 | C21: Flanders Artificial Intelligence European Digital Innovation Hub | D21: Given the technology potential of AI, there is an urgency to accelerate the adoption of AI by SMEs and other organisations. The Flanders AI EDIH intents to accelerate the adoption of AI among by an integrated service offering: (1.) Test before invest: initial advice, individual coaching, AI technical feasibility study, legal workshops and our special co-operation with commercial AI agencies, called "Start AI" (2.) Skills and training: inspiration sessions, thematic webinars & events, masterclasses and summer schools (3.) Innovation ecosystem and networking: talent & skills matchmaking, matchmaking on AI supply & demand, matchmaking on joint research and our large annual AI event called "Flanders AI Forum" (next edition: spring 2024). The Flanders AI EDIH strengthens the Flemish Industry Partnership (Industriepartnerschap), the Flanders AI Academy (VAIA) and the Knowledge Center Data & Society (Kenniscentrum Data & Maatschappij). The Flanders AI EDIH consists of complementary partners who guarantee a cross-sectoral and accessible Flemish operation, with a local physical presence in every Flemish province. Additionally, the EDIH is aligned and maintains direct links with existing innovation actors and initiatives (such as the spearhead clusters), the Flemish AI policy plan, the Flanders AI Research Program and Enterprise Europe Network (EEN) Flanders. At European level, the Flanders AI EDIH has ongoing collaborations through the AI DIH Network, the Smart Connectivity DIH Network (SCoDIHNet), the EPoSS Smart Systems EDIH Task Force, the Vanguard AI Pilot. | E21: Belgium | F21: Gilles Wuyts | G21: Kapeldreef 75, 3001 Leuven, Belgium | H21: EDIH | I21: https://flandersaihub.eu/ | J21: manufacturing and processing, transport mobility, textiles | K21: technological innovation, ecosystem building, sme support | L21: artificial intelligence decision support, big data, digital twins
A22: =A21+1 -> 21 | B22: 25 | C22: European Digital Innovation Hub Saarland | D22: EDIH Saarland is the digital innovation catalyst and integrator serving the needs of structural transformation in Saarland, the Federal State (Land) of Germany, by offering to regional SME’s, mid-caps and public sector entities a comprehensive service portfolio with the focus on Artificial Intelligence and other key enabling technologies. EDIH Saarland addresses essential regional innovation needs of green and digital transition, builds upon and makes a major contribution to the implementation of the regional innovation strategy and, at the same time, opens up its services to the entire EDIH network, thus putting the regional innovation strategy into the European context. The EDIH Saarland specialization in Industrial AI and AI for eGovernment is based on the significant and relevant testing and experimentation facilities, professional community of experts and regional innovation infrastructure. EDIH Saarland builds on existing partnership and various ongoing activities providing coordination and triggering a synergy effect. As an innovation broker, EDIH Saarland will facilitate and support the collaborative ecosystem including major research/innovation stakeholders with outstanding competences in the focus area, and local industrial and public sector organizations in need for digital transformation. The Hub’s work plan includes the set of activities aimed at making the EDIH Saarland’s service portfolio available for other EDIHs with the focus on further integration within the Greater Region and sectoral specialization (e.g. automotive industries). The EDIH Saarland consortium brings together the major regional RTD and innovation players, has established the privileged relations with the Saarland’s Government and other stakeholders, such as industrial clusters, research and education performers, business incubators etc., and, therefore, has ensured sustainable and lasting foundation for its operation. | E22: Germany | F22: Attique Bashir | G22: Eschberger Weg 46, Gewerbepark Geb. 9, 66121 Saarbrücken, Germany | H22: EDIH | I22: https://edih-saarland.de/ | J22: manufacturing and processing, automotive, retail, wholesale or distribution, metal working and industrial production | K22: sme support, technology transfer, knowledge transfer, prototyping, technological innovation | L22: artificial intelligence decision support, cyberphysical systems, human computer interaction, robotics, cybersecurity, digital twins, big data, sensors vision processing systems, simulation engineering and modelling, virtual reality
A23: =A22+1 -> 22 | B23: 26 | C23: MicroCyber | D23: The MicroCyber EDIH aims at establishing a set of services and infrastructures focusing on cybersecurity, to be offered to Micro and Small, and enterprises (MSE) in the South of Italy while also supporting public entities – both local and central – in understanding their cybersecurity needs. MSEs in the South of Italy need to improve their cybersecurity awareness and preparedness, as a key enabler for operating and thriving in the digital economy. Still, these MSEs are often unable to face the costs for accessing resources needed to improve their cyber-preparedness and are not able to find training and capacity building programs tailored to their needs and resources availability. To respond to these needs, MicroCyber offers a diversified set of services devoted to its target groups, including assessment of digital and cyber maturity and relevant needs, cyber-range activities to explore and test cybersecurity scenarios and solutions, personalised skills and training activities, networking, also via the involvement in ecosystems and events, as well as support services to access microfinance tools and other financial resources, which the MicroCyber EDIH is perfectly positioned to deliver leveraging the unique expertise of its Coordinator, Ente Nazionale per il Microcredito (ENM). At the same time, the MicroCyber can build on the unique combination of expertise available within its consortium, with public entities, universities, large SMEs associations, research consortia, private consultancy companies, all equally committed to deliver the highest quality in services, while offering networking and collaboration with the best digital expertises in Europe, via other EDIHs, the Digital Transformation Accelerator, and a variety of other networks in the digital domain available at the local and national level. | E23: Italy | F23: Giovanni Nicola Pes | G23: Via vittoria colonna 1, 00193 Roma RM, Italy | H23: EDIH | I23: https://www.microcyber.eu/2025/ | J23: manufacturing and processing, communityled local development, consumer products, financial, public administration, retail, wholesale or distribution | K23: sme support, knowledge transfer, technology transfer, technological innovation, ecosystem building | L23: cybersecurity, internet services applications
A24: =A23+1 -> 23 | B24: 27 | C24: Pomeranian Digital Innovation Hub | D24: Thanks to the project implementation, Pomeranian Digital Innovation Hub, which was selected by the Ministry of Development and Technology in the pre-selection, will be created. It will be managed by the consortium consisting of the Coordinator (COO), 20 Beneficiaries (BEN) and 11 Associated Partners (AP). Consortium will be coordinated by Pomeranian Special Economic Zone and Gdansk Science and Technology Park due to their important role in the local and regional ecosystem of innovation and entrepreneurship, and will be represented by entities with necessary expertise, experience, and required resources, which will allow successfully accomplish projects goals, tasks and activities. PDIH will act as one stop shop supporting mainly local SMEs, small mid-caps and public sector organizations with their digital and green transformation. PDIH will offer its clients the complete set of the following services: 1) Skills and training; 2) Test before invest; 3) Support to find investments; 4) Innovation ecosystem and networking. Its offer is a wide, yet well-thought-out and tailored to the identified needs of customers, catalogue of services (81 categories), which allows for the implementation of digital and green transformation. PDIH clients will gain access to new skills, technological and investment consulting, practical trainings, as well as access to the innovation ecosystem around PDIH allowing them to establish business relationships in the country and in the whole Europe, which will allow them to increase their competitiveness in the field of their operations by implementing digital solutions of the Industry 4.0. A significant part of the project in addition to the implementation of specialized services is networking and matchmaking activities. PDIH will be active in networking with other representatives of local, regional, national and European innovative ecosystem. | E24: Poland | F24: Marta Szalecka | G24: Ul. Trzy Lipy 3 bud.B IV p., 80-172 Gdansk, Poland | H24: EDIH | J24: manufacturing and processing, maritime, public administration, telecommunications | K24: sme support, ecosystem building, technological innovation | L24: artificial intelligence decision support, big data, cloud services, communication network, cybersecurity, digital twins, high performance computing, internet services applications, virtual reality, internet of things, locationbased applications, simulation engineering and modelling
A25: =A24+1 -> 24 | B25: 28 | C25: Innovation Hub for Smart Polymers and Digital Technologies | D25: Polytronics is dedicated to supporting SMEs in their digital transition, in respect of Artificial Intelligence (AI), with a focus on the polymer industry: plastics, textiles, elastomers & rubbers, composites. Indeed, these industries are often traditional and conservative (notably in the textile sector with quite often production machines lacking mere sensors) yet suffer from the lack of data exploitation even though their manufacturing lines may be equipped with sensors. Polytronics aims to help companies in the polymers industry in their digital maturity by leveraging the use of Artificial Intelligence (AI) based on exploitable data from their products and manufacturing processes. Polytronics gathers 7 specialists in AI, robotics, data management and exploitation, 3 partners specialised in sensors integration, 2 partners specialised in mechatronics to support proofs of concept in industry, 5 technical centers specialised in targeted polymer sectors, and 2 innovation clusters. Experts in polymers will support AI experts in understanding and adapting the needs and pain point of the SMEs in the polymer industry. Therefore, SMEs will benefit from the crossed expertise to facilitate the implementation of AI in their business, without negative disruption of their business. Polytronics dedicate 70% of its budget, 3.3M€ over 3 years to the provision of services to SMEs. Besides this core activity, Polytronics partners will merge and update its website and two key platform, a marketplace and a knowledge management platform, to implement a web portal which will be the one-stop-shop for SMEs, therefore facilitating their access and user journey. This web portal will allow notably gathering data and indicators to feed the DTA with the digital maturity evolution of the polymer sector targeted by Polytronics. Finally, clustering activities, communication and dissemination will allow implicating Polytronics in the whole EDIH network. | E25: France | F25: Adèle Seguin | G25: 180 rue pierre et marie curie maison des entreprises, 01115 Bellignat, France | H25: EDIH | I25: https://polytronics.eu/ | J25: manufacturing and processing, polymers and plastics, textiles, nmp nonmetallic materials basic processes | K25: circular economy, prototyping, ecosystem building, sme support, technological innovation | L25: artificial intelligence decision support, additive manufacturing, chemical engineering plants, products, laserbased manufacturing and materials processing, sensors vision processing systems
A26: =A25+1 -> 25 | B26: 29 | C26: PRODUTECH DIH | D26: As European Digital Innovation Hub, PRODUTECH DIH has the mission to promote the digitalisation of the manufacturing industry, through a consistent and coherent dual intervention directed to both production technologies and manufacturing sectors, leveraging the role that production technologies assume in the digital and green transformation of the several sectors of the manufacturing industry. Gathering a critical mass of unique capacities, infrastructures, competencies, capabilities and associated services, and having a solid relational capital with the ecosystem of stakeholders, a track record of European intervention and of corridors with other EDIHs, PRODUTECH DIH articulates, provides and makes available to the industry, and pertinent stakeholders, a coherent set of support services within the 4 main functions attributed to European Digital Innovation Hubs: Test before invest, Skills and training, Support to find investments and Dynamization of the innovation ecosystem and networking. PRODUTECH DIH is a consortium of 19 organizations, gathering the Portuguese cluster of production technologies for manufacturing, a science park/incubator, industry’s sector-oriented technology centers, research and technology organizations and higher education and vocational training organizations, with multiple locations across Portugal, acting as multipliers of digital capacities and as access points to the hub, to the European Network of DIHs, pertinent stakeholders, such as Enterprise Europe Network, and initiatives, and providing key support services, within the domains foreseen by the Digital Europe Programme, towards the digital and green transformation of the industry. PRODUTECH DIH delivers a solid unique value proposition: (1) consistent consortium towards the digital and green transformation of the industry, (2) European intervention capacity and ambition and (3) a strategic synergic intervention Local-Regional-National-European. | E26: Portugal | F26: Pedro Miguel ROCHA | G26: Rua dos Platanos 197, 4100-414 Porto, Portugal | H26: EDIH | I26: https://dih.produtech.org/en | J26: manufacturing and processing, metal working and industrial production, aeronautics, automotive, construction assembly, consumer products, defence, education, energy, electricity, energy, energy, fuels and petroleum engineering, environment, financial, food and beverages, leather, maritime, nmp nonmetallic materials basic processes, paper and wood, polymers and plastics, public administration, retail, wholesale or distribution, security, telecommunications, textiles, tobacco, transport mobility, transport sector | K26: circular economy, ecosystem building, field trial, finance, innovation management, knowledge transfer, prototyping, public sector innovation, regional development, smart specialisation strategies, sme business development, sme support, technological innovation, technology transfer, vocational training | L26: artificial intelligence decision support, high performance computing, cybersecurity, additive manufacturing, big data, blockchain and distributed ledger technology dlt, chemical engineering plants, products, cloud services, communication network, cyberphysical systems, digital twins, displays, gamification, human computer interaction, industrial biotechnology, internet of things, internet services applications, laserbased manufacturing and materials processing, locationbased applications, logistics, micro and nanoelectronics, optoelectronics, mobility, new technologies for audiovisual sector media, organic and large area electronics, photonics, quantum technologies computingcommunication, robotics, semiconductors and nanotechnology, sensors vision processing systems, simulation engineering and modelling, software architectures, virtual reality
A27: =A26+1 -> 26 | B27: 30 | C27: Smart, Resilient and Sustainable Communities – European Digital Innovation Hub | D27: Smart, Resilient and Sustainable Communities – European Digital Innovation Hub The SRC-EDIH will support state and local governments and SMEs in testing products, solutions, and components in a real environment and upgrading their digital processes and the associated business models while aligning the growth opportunities with the Sustainable Development Goals. Our vision is to become a leading EDIH in Southeast Europe, contributing to fostered digitalization of manufacturing SMEs and digital transformation of public administration through advanced digital technologies by considering the economic, environmental, and social development pillars. Through advanced interaction with national and European DIHs, SRC-EDIH will bring awareness of the importance of digital transformation for sustainable growth and serve as a one-stop point of know-how, guidelines, and support to increase digitalization in governmental and industrial institutions. In addition, SRC-EDIH will provide access to prototyping and test environments to accelerate the adoption of new digital technologies and skills and advance the current digital solutions. Moreover, it will provide (i) support for building an industrial ecosystem of firms with broad expertise in different fields that offer complementary services or products through conferences, events, and workshops; (ii) and support for access to European and national public and private funding to strength the firms’ capacity of introducing digital innovation and I increasing their competitiveness. | E27: Slovenia | F27: Vesna Čolič | G27: Podbreznik 15, 8000 Novo mesto, Slovenia | H27: EDIH | J27: manufacturing and processing, automotive, environment, public administration, education | K27: circular economy, technology transfer, prototyping, public sector innovation, sme support, vocational training | L27: high performance computing, artificial intelligence decision support, cybersecurity, robotics, blockchain and distributed ledger technology dlt
A28: =A27+1 -> 27 | B28: 31 | C28: Swedish network for Sustainable Digitalisation and Human-Centric Factory Transformation | D28: The objective of the Swedish EDIH for smart manufacturing industries, Swedish network for Sustainable Digitalisation and Human-Centric Factory Transformation (ShiftLabs) is to strengthen, generate and promote services targeted at manufacturing SMEs that support their digital transformation and work towards sustainable manufacturing industries. The proposed EDIH is based on a national hub with regional nodes. The consortium supports a structure of regional nodes with a comprehensive offer of services to SMEs. Each regional node follows the template of a “one stop shop”, a single point of contact with verified experience and expertise in supporting SMEs, paired with an academic partner that has relevant state-of-the-art production research as well as training and education for professionals in the field. Each node also maintains a local network of relevant collaboration partners to ensure the supply of applicable services, for example through local science parks. The nodes are supported cross-sectionally by core partners with wide and specific expertise in digital technologies, as well as testbeds, data centres, and facilities to support SMEs with their individual needs related to, for example, artificial intelligence, cyber security, industry 4.0 related technologies, and HPC. The hub partners already maintain a strong European connection, with several of them already being fully operational Digital Innovation Hubs. The strong national and European integration ensures that the ShiftLabs will be a valuable resource for the manufacturing SMEs, as well as an effective partner in the European network of EDIHs. To ensure the relevance of the hub, the proposal has letters of support from the involved Regions (Region Västmanland, Region Sörmland, Västra Götalandsregionen, Region Stockholm), Produktion2030 (national funding programme for production research), the Scandinavian Automotive Supplier Association (FKG), IUC (industrial development center), and ALMI. | E28: Sweden | F28: Johan KOSTELA | G28: Hogskoleplan 1, 721 23 Vasteraas, Sweden | H28: EDIH | I28: https://shiftlabs.eu/ | J28: manufacturing and processing, automotive, metal working and industrial production | K28: technological innovation, technology transfer, sme support, circular economy | L28: additive manufacturing, artificial intelligence decision support, cyberphysical systems, digital twins, human computer interaction, internet of things, robotics, sensors vision processing systems, simulation engineering and modelling
A29: =A28+1 -> 28 | B29: 32 | C29: Transilvania Digital Innovation Hub | D29: The European Digital Innovation Hub in Transilvania (TEDIHT) aims to address industry and societal challenges through innovation driven by digital technologies. We use cutting edge technologies like AI, HPC and Big Data to enable digital transformation processes, provide green/sustainable solutions that improve productivity, competitiveness, growth, and wellbeing at regional, national, EU, and international levels. TEDIHT's general objective is to provide a complete set of digital transformation and innovation services for (1) SMEs and (2) public sector organisations (PSOs) conducting non-economic activities from the NW region of Romania and, through the EDIH network, at EU level. TEDIHT’s primary specialisation and services use AI, HPC and Big Data to support the green and digital transformation of SMEs and PSOs in the fields of Digital Health and Industry 4.0, leading to economic development, competitiveness and societal progress. TEDIHT is based on a 3-phase process: Understand > Innovate > Scale, and 2 alternative Client Journeys (Minimal and Optimal) through which we will provide significant innovation and digital transformation services, worth up to 100K EUR, to 87 SMEs and/or PSOs primarily from Digital Health and Industry4.0 sectors, over a 3-year period, from a 10x pool (870 beneficiaries) engaged in our innovation ecosystem’s services. TDIH’s offers a customised service list adapted to the challenges and needs of beneficiaries from NW region of Romania, validated in several EU projects, covering the 4 functionalities of a digital innovation hub: (1) networking and ecosystem building, (2) test before invest, (3) skills and training and (4) support to find investment. TDIH consortium convenes a regional innovation ecosystem orchestrated by Transilvania IT Cluster, the 3 main universities in the region UBB, UTCN and UMF, a national research institute – INCDTIM - and an industry liaison office, OLI Hygia. | E29: Romania | F29: Bianca Muntean | G29: Str. Constantin Brâncuși nr. 55-57-59, 400458 Cluj-Napoca, Romania | H29: EDIH | J29: manufacturing and processing, health care, energy, agricultural biotechnology and food biotechnology, smart city | K29: technological innovation, ecosystem building, innovation management, prototyping, finance, sme business development | L29: artificial intelligence decision support, high performance computing, cybersecurity, quantum technologies computingcommunication, software architectures, robotics, internet of things, big data
A30: =A29+1 -> 29 | B30: 33 | C30: Umbria Digital Data | D30: UDD aims at accompanying Small and Medium Enterprises (SMEs) and Public Administrations (PAs) towards the advanced digital transition in the Umbria region. Through its services, centered on the three main digital technologies (Artificial Intelligence - AI; High Performance Computing - HPC; Cybersecurity), UDD intends to cover some specific areas, such as manufacturing, energy, and life science with a significant impact on the strategic sectors of commerce and tourism. UDD has a multi-sector focus and it targets on PAs and SMEs that have an organizational structure suitable to digitization procedures. The objective is to enhance the regional specific characteristics while joining the European EDIH Network in order to increase exchange opportunities providing businesses and PAs with the widest range of digital services and advice. UDD main goals towards SMEs and PAs are: The development and the implementation of AI capabilities; The development and the implementation of HPC competences; The acquisition of digital competences in Cybersecurity and advanced technologies; A greater awareness about sustainability and the ethical use of AI. UDD will work mainly on some specific focused areas, as: • Machine learning: AI applied to industry, Blockchain; Data Analytics and HPC; • Advanced manufacturing for the innovation of products and industrial procedures; • Life science technologies, also concerning emergency management; • Advanced materials and nano-materials employed in innovative business activities in the regional territory; • IoT, Automation, Embedded Systems; • Green Economy, Energetic Efficiency, Logistics and resources management. UDD includes 13 partners: 5 research and technological transfer institutes (among which there are the University of Perugia and The National Institute of Nuclear Physics that are the main UDD technical partners), 4 trade associations, 2 regional agencies, a Digital Innovation Hub and an Institute for Higher Technical Training. | E30: Italy | F30: Luca Angelini | G30: Via palermo 80/a, 06124 Perugia PG, Italy | H30: Seal of Excellence | J30: manufacturing and processing, health care, travel and tourism, communityled local development, cultural and creative economy, smart city | K30: ecosystem building, innovation management, technology transfer, sme support | L30: artificial intelligence decision support, cybersecurity, high performance computing, big data, blockchain and distributed ledger technology dlt, digital twins, internet of things
A31: =A30+1 -> 30 | B31: 34 | C31: WalHub, to boost the digital transformation of manufacturing companies and the adoption of key technologies - i.e. AI, HPC, Cybersecurity and IoT - in their industrial and supply chain processes | D31: Lying at the heart of Europe, Wallonia (the French-speaking region of Belgium) economic history is closely linked to the role of industry, with a strong industrial past in machinery manufacturing and metallurgy. Today, manufacturing is still the driving force behind Wallonia's exports and prosperity. Nevertheless, the foundations of the manufacturing industry need to be considerably strengthened in order to increase technological excellence as well as to facilitate the green and digital transition of the region. WalHub, the regional EDIH, will boost the Walloon manufacturing business helping them to tackle challenges linked to customer expectations by accelerating or enhancing their digital maturity, through experimentation of key technologies (e.g. AI, HPC, CS and IoT), training and upskilling workers to meet the market needs, attracting investments, linking them to the Walloon ecosystem to ease implementation of digital technologies in their production processes and supply chain. Finally, WalHub will connect with the network of EDIHs by offering its services to SMEs from other regions across Europe and will actively engage with other EDIHs to respond promptly to the digital needs of Walloon manufacturing businesses. To support Walloon manufacturing business to achieve greater competitiveness and sustainability at regional level, WalHub, brings together a consortium of complementary and experienced partners that will provide a comprehensive set of services aiming at accelerating the green and digital transformation of industrial and supply chain processes. WalHub is led by the industry and technology federation (Agoria) and involve 2 clusters active in Manufacturing and Transport and Logistics (MecaTech and Logistics in Wallonia), 4 research and competence centers (Sirris, Cenaero, Cetic, Multitel) and an economic development partner (IDELUX). In this project, WalHub also benefits from the support of the Walloon Digital Agency (Agence du Numérique). | E31: Belgium | F31: Emilie Parthoens | G31: A. Reyers 80 diamant building, 1030 Bruxelles, Belgium | H31: EDIH | I31: http://www.walhub.be | J31: manufacturing and processing, agricultural biotechnology and food biotechnology, health care, polymers and plastics, aeronautics, space, paper and wood, construction assembly | K31: technological innovation, ecosystem building, knowledge transfer, prototyping, circular economy, finance | L31: internet of things, artificial intelligence decision support, cybersecurity, high performance computing
A32: =A31+1 -> 31 | B32: 35 | C32: Innovation for Competitiveness and Advance Manufacturing | D32: i4CAMHUB has been an EDIH since 2017, is a part of DIHNET, has signed agreements with other EDIH to provide services together, and yet there is still place to grow and become more of a reference in the region, in its main fields of work which are the sectors of agrifood and metal manufacturing, and AI as technology (in a second level, also cybersecurity, HPC, AR/VR, human-machine interaction and others). To do this, this project is focused on developing and establishing relevant activities-services, mainly for SMEs, scaleups, startups, entrepreneurs, but also for the general population. The first set of activities include three work packages: 2, 4 and 5, focused respectively on: - TEST BEFORE INVEST solutions that allow entities or entrepreneurs to investigate how relevant technological solutions would fit their current lines of work or new lines they want to develop without having to make the investment beforehand;S - Facilitating FUNDING FOR DIGITALIZATION or to TO START-UP BUSINESSES OR LINES OF WORK; - NETWORKING SOLUTION, facilitating spaces from where to work or events to get to know possible partners interested in applying the solutions developed by users, in getting together to develop new ones or who can provide them with technology they are needing. The second one (WP3) is focused on training: - Different COURSES, WEBINARS, INFO-DAYS and WORKSHOPS will be offered to diverse target groups including active population, students, unemployed people and people in risk of social exclusion with the intention of improving their chances to get relevant employments and improve their general situation. The fact that Castilla La Mancha includes large areas of rural space scarcely populated is taken into account and I4CAMHUB intends to facilitate access to these resources also in those areas. I4CAMHUB also has a relevant intent to actively engage with other EDIHs to maximise its reach and improve the general position of Castilla La Mancha in the general European scope. | E32: Spain | F32: Cristina Conejo | G32: Ctra Pedro Munoz km1 PC. 51, 13700 TOMELLOSO Ciudad Real, Spain | H32: EDIH | I32: https://www.i4camhub.com/es/home | J32: manufacturing and processing, metal working and industrial production, energy, energy, fuels and petroleum engineering, food and beverages, retail, wholesale or distribution, smart city, environment, construction assembly, nmp nonmetallic materials basic processes, communityled local development, automotive, transport mobility, consumer products, telecommunications, transport sector, defence, polymers and plastics, textiles, aeronautics, agricultural biotechnology and food biotechnology, space, personal services, travel and tourism | K32: prototyping, technological innovation, technology transfer, regional development, innovation management, knowledge transfer, smart specialisation strategies, sme business development, sme support | L32: artificial intelligence decision support, big data, simulation engineering and modelling, virtual reality, robotics, digital twins, sensors vision processing systems, locationbased applications, internet of things, cybersecurity, logistics, additive manufacturing, laserbased manufacturing and materials processing, cloud services, high performance computing, quantum technologies computingcommunication
A33: =A32+1 -> 32 | B33: 36 | C33: AI driven digital transformation of SMEs - towards Industry 5.0 production processes | D33: The EDIH AI5production has a regional focus to the north-east of Austria and mainly addresses manufacturing SMEs and mid-caps in Austria. The overall objective of the EDIH AI5production is to consolidate the Industry 4.0 maturity of SMEs and mid-caps in the region and transfer them to Industry 5.0 companies by providing all four foreseen service pillars of an EDIH. This will be achieved by offering established test before invest infrastructure and excellent services and support in the areas: Artificial Intelligence, Design, Digital Production, and Cybersecurity. This is possible due to an experienced consortium. 2 pilot factories are at the front: Pilot Factory 4.0 from TU Wien and LIT Factory of Johannes Kepler University Linz. The whole consortium consists of 5 Competence Centers for Excellent Technologies, 3 Non-university research organization, 3 Universities, 2 industrial partners, 1 Business incubator and the Platform Industry 4.0 Austria and EIT Manufacturing East. | E33: Austria | F33: Franz Suemecz | G33: Karlsplatz 13, 1040 Wien, Austria | H33: EDIH | J33: manufacturing and processing | K33: ecosystem building, field trial, prototyping, finance, technological innovation, circular economy, sme support | L33: additive manufacturing, artificial intelligence decision support, cybersecurity, digital twins, robotics, virtual reality, sensors vision processing systems
A34: =A33+1 -> 33 | B34: 37 | C34: Robotics, Control and Decision Systems Digital Innovation Hub at the Cyprus University of Technology | D34: We are the Robotics, Control, and Decision Systems (RCDS) laboratory and Digital Innovation Hub (DIH) at the Cyprus University of Technology. We are the first robotics laboratory in Cyprus (established in 2011) Since then, we have developed externally funded activities worth more than 26 million euros. We engage in research, technology development, innovation, and commercialisation activities. The team has decades of combined robotics, technology, product development, and business experience in the US and Europe. We have worked with commercial entities of all sizes (start-ups to multinationals) as well as academia, government agencies and NGOs. Keywords: entrepreneurship, algorithm development, open software, open hardware, robotics, decision making, logistics | E34: Cyprus | F34: Associate Professor Savvas G. Loizou | G34: 45 kitiou kyprianou street, dorothea bldg., office 507, 3041 Limassol, Cyprus | H34: DIH | I34: https://www.rcdslab.org/ | J34: manufacturing and processing, maritime | K34: circular economy, field trial, innovation management, knowledge transfer, prototyping, public sector innovation, sme support, technological innovation, technology transfer | L34: artificial intelligence decision support, big data, cyberphysical systems, digital twins, logistics, robotics, simulation engineering and modelling
A35: =A34+1 -> 34 | B35: 38 | C35: European Digital Innovation Hub Boosting Additive Manufacturing through Digital Services | D35: AM-EDIH is a European Digital Innovation Hub providing world-class services for boosting industrialisation of Additive Manufacturing ("AM") through digitalisation and thereby increasing sustainability and competitiveness of European manufacturing industry. The target clients of AM-EDIH, to which digital AM services will be provided, are 1) SMEs and small mid-caps being i) manufacturers, ii) product developers and iii) solution providers for the new value chains connected to the rapid digitalization of industry, among large enterprises and 2) Public healthcare sector and particularly university hospitals where advanced healthcare services are offered using AM. AM-EDIH has its basis in Western Sweden (Region of VästraGötaland, "RVG") where manufacturing industry constitutes almost half of the region's economy and where research and innovation, e.g. at Chalmers University of Technology ("Chalmers") and Research Institutes of Sweden ("RISE"), is heavily focused on digital manufacturing, and specifically so on digital AM. Moreover, the region's University Hospital (Sahlgrenska) is one of Sweden’s largest hospitals and a hub for strong innovation and clinic research activities, also in AM, in close and broad cooperation with academia, industry and patients. AM-EDIH will focus on developing RVG into a world-leading region for digital AM that can inspire and support other regions in Europe to adopt digital AM to increase sustainability and competitiveness. Through the Swedish regional network of 21 Industrial Development Centres it will also reach the target groups nation-wide. For AM-EDIH it will be very important to network with other EDIHs and EEN to reach other European regions and clients and exchange knowledge, competence, and good practises of digitalisation and thereby contribute to the digital transformation of the European manufacturing industry. RVG, being the 11th most innovative region in Europe (2021), has excellent conditions for achieving this. | E35: Sweden | F35: Lars Nyborg | G35: Chalmersplatsen 4, 412 96 Goteborg, Sweden | H35: Seal of Excellence | J35: manufacturing and processing | K35: sme support, knowledge transfer | L35: additive manufacturing
A36: =A35+1 -> 35 | B36: 39 | C36: CONNECT5 | D36: CONNECT5 – DIH for Connectivity, CPS, IoT, Cloud/Edge and Data Analytics aims to create and operate a national and European reference DIH supporting the digital and green transformation of SMEs and public organizations. CONNECT5 is a collaborative network, in the form of a Consortium of 12 entities (RTO, polytechnic institutes, universities), with high level of expertise in digital technologies, state-of-the-art infrastructures and a deep nation-wide network of contacts (companies, business associations, public entities, etc.) bringing together their complementary expertise and assets, to create a unique value platform. CONNECT5’s will leverage on its capabilities based on Cyber-Physical Systems (CPS), Internet of Things (IoT), Communications networks (5G and 6G), infrastructures (Cloud and Edge Computing), Big Data platforms and analytical data processing, supported by Artificial Intelligence (AI), Cybersecurity and High-performance computing (HPC) when required, enabling the target entities to evaluate its impacts and the feasibility to their business before further investing in it. The services provided by CONNECT5 will be based on the definition of a digital transformation strategy identified in close cooperation with the user materialised on a strategic road map validated through the 4 main domains: i. Test before invest; ii. Skills and training; iii. Support to find investment; iv. Innovation ecosystem and networking. Included in the action plan is also the Digital Maturity Assessment, transformation proposal and acceleration with the DTA. CONNECT5 will provide a wide range of services that will enable any beneficiary to access the latest knowledge, expertise and technology with a special focus on the connectivity dimension for testing and experimenting digital innovation relevant to their activity, matching their needs with digital solutions already available or in an advanced phase of deployment. CONNECT5 expertise is reinforced by national projects like 5GO (focused on communication technologies), AUGMANITY (focused on I4.0) and CITYCATALYST (Focused on smart cities) among other activities (OASC, Gaia-X). | E36: Portugal | F36: Vasco Lagarto | G36: Campus universitario da universidade de aveiro, 3810-193 Aveiro, Portugal | H36: Seal of Excellence | I36: https://connect5.pt/ | J36: manufacturing and processing, smart city, construction assembly | K36: sme support, ecosystem building, knowledge transfer, field trial, technology transfer | L36: big data, cyberphysical systems, communication network, cloud services, internet of things, digital twins
A37: =A36+1 -> 36 | B37: 40 | C37: IMPROVING THE COMPETITIVENESS OF SMEs AND PSOs IN THE SOUTH-EAST REGION OF BULGARIA THROUGH INTEGRATED INNOVATIVE DIGITAL SOLUTIONS | D37: The main objective of DIGIHUB is to support the digital transformation of SMEs and PSOs in the SouthEast region of Bulgaria by providing a wide range of services in the context of regional/municipal strategies aiming to boost the innovative potential of SMEs and to improve the digitalisation of public services deliveries. The DIGIHUB services are structured on four pillars, and are based upon an strong expertise of the entities involved in the Consortium with an special emphasis on the domains of AI, cybersecurity, big data, ICT and distributed ledger technologies, and with focus on the leading economic sectors of the SouthEast region (energy/health/transport/logistics/tourism). The target users of DIGIHUB services are: -the companies active in the leading economic sectors of the SouthEast region with the main target to reach at least 166 SMEs with test before invest and business advisory support, accompanying the most prominent 30 digital projects in the process of searching additional funding opportunities to implement digital transformation plans; -the municipalities of Burgas,Pomorie,Sliven, the state company "Port infrastructure" and the ILPB (Industrial and Logistic Parк-Burgas), and two universities, with the aim to support the digital transformation of public services deliveries and ensuring that DIGIHUB plays a key brokering role between local administrations and relevant companies providing e-government services and technologies. DIGIHUB organization is built upon a solid structure and consolidated expertise involving ICT Cluster Burgas, Burgas municipality, DINT Foundation, two universities (UNIAZ/BFU), together with the BAS-Burgas and AIBEST, offering an unique base to position DIGIHUB as the key EDIH in the SouthEast region of Bulgaria, and as the main window bridging technological complementarities with other EDIHs at national and international level, and supporting actively the DTA on its engine role for the monitoring of EDIHs services. | E37: Bulgaria | F37: Petko Georgiev | G37: 28, Kniaz Alexander Batenberg St., 8000 Burgas, Bulgaria | H37: Seal of Excellence | I37: https://digihub.bg | J37: manufacturing and processing, construction assembly, cultural and creative economy, travel and tourism, automotive, maritime, smart city, education | K37: technological innovation, circular economy, ecosystem building, finance, innovation management, prototyping, public sector innovation, smart specialisation strategies, vocational training | L37: artificial intelligence decision support, digital twins, cloud services, data, blockchain and distributed ledger technology dlt, cybersecurity, internet services applications, logistics, virtual reality, mobility
A38: =A37+1 -> 37 | B38: 41 | C38: Regional Center for Digital Solutions and Innovation NCIZ | D38: This project proposal envisages the creation of a European Digital Innovation Hub by the name of Regional Center for Digital Solutions and Innovations NCIZ (RCDSI NCIZ) on the territory of Industrial Park Sofia-Bozhurishte. The project aims to construct innovative digital infrastructure supporting the digital transformation of the companies in the field, mostly SME and small mid-caps, as well as public sector organisations performing non-profit activities in view of increasing their competitiveness through assimilation and implementation of the Industry 4.0 paradigm. An innovative research infrastructure will be built to serve the area's investor companies as well as future entrepreneurs, researchers, innovators, scientists, citizens, local and regional administrations. The centerpiece of the center will be a virtual reality lab that will provide users with 3D laser visualization of buildings, machines and new products before launching them. This will also help to stimulate innovation and the introduction of new technologies, increase the technological potential for staff qualification. The implementation of the project will also increase the interaction and exchange of knowledge between scientific organizations, business business and the municipality. | E38: Bulgaria | F38: Dobrinka Vitcheva | G38: 1, angel kanchev str., 1000 Sofia, Bulgaria | H38: Seal of Excellence | J38: manufacturing and processing, metal working and industrial production | K38: technological innovation, prototyping, sme support | L38: artificial intelligence decision support, digital twins, laserbased manufacturing and materials processing, simulation engineering and modelling, virtual reality
A39: =A38+1 -> 38 | B39: 42 | C39: ARTES 5.0 Restart Italy | D39: ARTES 5.0 - Restart Italy aims at a widespread nationwide adoption of digital technologies, with focus on Artificial Intelligence and Robotics, to nurture sustainable, human-centric and resilient value chains in line with the Digital Europe Programme. ARTES 5.0 will operate as a network of hub and spokes of highly qualified aggregations of competences and stakeholders, designed to transfer skills to Micro, Small and Medium Enterprises and to Public Administration. ARTES 5.0 will offer innovation services purposely designed to accelerate digital and ecological transition in different economic sectors such as health and quality of life, sustainable manufacturing, regeneration economy, creative and cultural industry. Special attention will be devoted to the crucial energy sector. ARTES 5.0 will also exploit technology to reduce the number and severity of accidents at work.ARTES 5.0 will be an access point for companies and PA to an interconnected innovation ecosystem of knowledge, skills, and infrastructures of excellence, distributed throughout the Italian territory and connected to several European EDIHs. ARTES 5.0 will offer users training, access to investments for innovation and advanced technical facilities for test-before-invest available in three Competence Centers (ARTES 4.0, MediTech and START 4.0) promoted and co-funded by the Italian government, to be further expanded within Digital Europe. ARTES 5.0 initiatives will be spread to users through a charter of services, designed to make the effects of innovation tangible in real business scenarios, overcoming cultural and geographical barriers. The Governance of ARTES 5.0 has been designed to achieve efficiency and effectiveness, while ensuring transparency and participation. In order to increase its impact from a local and national level to a broader European level, ARTES 5.0 has signed MoUs and LoIs with several EDIH proposals, sharing vision, strategy, and models, to strengthen initiatives, promote synergies | E39: Italy | F39: Paolo Dario | G39: Viale Rinaldo Piaggio 34, 56025 Pontedera PI, Italy | H39: EDIH | J39: manufacturing and processing, health care, travel and tourism, cultural and creative economy, environment, financial | K39: circular economy, ecosystem building, innovation management, technology transfer | L39: artificial intelligence decision support, robotics
A40: =A39+1 -> 39 | B40: 43 | C40: EDIH Grand Est - Accelerate digitalisation of manufacturing sector in Grand Est | D40: Fostering the digitalization of SMEs and Midcaps is a major objective of regional policies of Region Grand Est (S3, Regional scheme for economic development, innovation, and internationalization,), which is the third most industrialized French region. To do so, the regional authorities have defined a transformation pathway for companies and set up a digital cluster (GET Digital), managed by Grand E-Nov+, the regional innovation and attractiveness agency, that brings together the key public and private stakeholders. Furthermore, the GE territory hosts national and European renowned technology platforms regarding IA, cybersecurity, HPC, and immersive technologies. Nevertheless, these digital infrastructures and expertise have not sufficiently benefited regional companies, due to the poor connections and weak organized links between digital platforms and SMEs from key sectors. The objective of the EDIH GE is to create a one-stop-shop hub to foster the digitalization of industrial SMEs and midcaps (automotive, engineering, mechanics, textile,...), that require support regarding identification, testing, and integration (training, funding) of advanced technologies such as AI or cybersecurity, and HPC in industrial processes. With a budget of 3.8 ME, EDIH GE will deliver services (170 TBI, 500 Trainees, 16 networking events (320 participants), and 80 funding services) in three years to at least 300 companies. To deliver this strategy, GEN+ will coordinate a consortium of 11 partners that gathers 7 Universities and Engineering schools, two TTOs that manage 19 platforms and provides advanced training services, and the regional chamber of commerce that will be active to detect and qualify use cases in SMEs and mid-caps. The EDIH GE partners will be plugged into the DTA, with EEN (GEN+ and CCI GE are members) and with French and European EDIH all along its 770km of borders. EDIH GE will be co-funded by Region Grand Est (40%) and private resources (10%). | E40: France | F40: Jean-Jacques Bernardini | G40: 30 rue François Spoerry, 68100 Mulhouse, France | H40: EDIH | J40: manufacturing and processing, automotive | K40: sme support, technology transfer, finance, sme business development | L40: artificial intelligence decision support, cybersecurity, high performance computing
A41: =A40+1 -> 40 | B41: 44 | C41: IP4FVG EDIH - Industry Platform for Friuli Venezia Giulia EDIH | D41: Industry Platform 4 FVG - EDIH is the European DIH for Friuli Venezia Giulia (FVG) Region, Italy. Although the Region ranks among the top national innovators, its economy needs support to boost the benefits of digital & green transformation for SMEs & Public Administrations. Due to its geographical position on the border with Slovenia, Austria, Croatia, its activities acquire a transnational value, especially for Central Eastern Europe. In line with S4 priorities, it promotes the use of AI, HPC and Cybersecurity capacities and in 3 relevant sectors for FVG economy: Manufacturing, Agrobiotech and Energy&Environment. IP4FVG EDIH represents the evolution and scale-up of the regional DIH IP4FVG, fully operational since 2018 (supported by Sistema ARGO, an Institutional Protocol by the National Ministers of University and Research, Economic Development and Friuli Venezia Giulia Region) by a novel set of technologically specialized support services to boost adoption of digital and green technologies by regional SMEs and PAs and by granting access to the existing technological infrastructures for test-before-invest and skills building activities. It will also enable the outreach to complementary services and infrastructures provided by other EDIHs. Actions will be developed to support digitalization policies and stimulate the deployment of e-Government solutions. IP4FVG EDIH engages an ecosystem for digital innovation players, provides services for testing before investing, supports finding investments, financial and fiscal incentives, offers training and upskills services on digital capacities and fosters exchanges and enables local and extra regional SMEs and PAs to get access to the services and infrastructures by the European network of EDIH. A partnership composed by the main regional players representative of the quadruple helix ecosystem ensures competences and commitment to move towards the twin transition. | E41: Italy | F41: Martina Terconi | G41: Padriciano, 99, 34149 Trieste TS, Italy | H41: Seal of Excellence | I41: https://www.ip4fvg.it/ | J41: manufacturing and processing, agricultural biotechnology and food biotechnology, energy, environment, construction assembly, cultural and creative economy, health care, life sciences, public administration, metal working and industrial production, smart city, public administration | K41: innovation management, knowledge transfer, sme support, circular economy, ecosystem building, prototyping, public sector innovation, sme business development, technological innovation, smart specialisation strategies, regional development, field trial | L41: artificial intelligence decision support, internet of things, high performance computing, cybersecurity, simulation engineering and modelling, additive manufacturing, mobility, virtual reality, sensors vision processing systems, digital twins, cyberphysical systems, quantum technologies computingcommunication, robotics, new technologies for audiovisual sector media, industrial biotechnology, big data, human computer interaction
A42: =A41+1 -> 41 | B42: 45 | C42: Luxembourg Digital Innovation Hub | D42: L-DIH is the nation-wide EDIH for Luxembourg (LU). L-DIH focuses on the Manufacturing sector, including logistics. Technologically, we will focus mainly on HPC and Cybersecurity to become a EU EDIH lighthouse in the 2. As one-stop-shop for digital transformation, we will also support the digital transformation endeavours for any technologies (AI, 5G, IoT, robotics...). Our consortium consists of 5 key partners in the LU ecosystem (the national innovation agency, 1 RTO, 1 university and 2 competence centres), 3 associated partners, working closely with 2 national ministries (economy and communication). L-DIH expands on the existing mature innovation ecosystem by deploying 18 new digital transformation services. These services were carefully designed to on one hand integrate L-DIH in the LU ecosystem and leverage the existing services, and on the second hand bridge with the EU digital initiatives. With the consortium, L-DIH bridges with the HPC and Cybersecurity national competence centres to seamlessly leverage the EU efforts in both. We will work according to a structured funnel approach from Inform > Inspire > Engage declined in the 4 EDIH pillars. In stage 1, Inform, we show digitalization opportunities and benefit. In stage 2, Inspire, we work with small groups of common interest SMEs, In stage 3, Engage, we work directly with the SME in a customized digital transformation roadmap. Over 3 years, we will inform more than 250 SMEs multiple time, inspire 125 multiple times and engage at least 72 SMEs. We will self-assess our services and methodologies, along with the continuous market and ecosystem evolutions. We will draw expect to discover which best practices which will be exchanged with the EDIH network. As a member of the EDIH network, we establish a cross-border cooperation with the EDIH from the Greater Region (BE, FR, DE) and we will establish more than 15 corridors. We will bridge heavily with the DTA to become a vibrant member of the EDIH network. | E42: Luxembourg | F42: Philippe Mayer | G42: 5 avenue des hauts fourneaux, 4362 Esch sur alzette, Luxembourg | H42: EDIH | J42: manufacturing and processing | K42: ecosystem building, field trial, finance, innovation management, sme support, vocational training | L42: high performance computing, cybersecurity, artificial intelligence decision support
A43: =A42+1 -> 42 | B43: 46 | C43: Mid Sweden Industry and GovTech EDIH | D43: MIGHTY EDIH (MIGHTY) will contribute to the European digital and green transition of SMEs, small-midcaps and public entities (Target groups), with special focus on Manufacturing industry and Govtech all over Europe. Building on a vast experience of bringing these sectors together in already ongoing cross-border collaborations, this combination will be a strong driver for innovative and silo-breaking digital and green transition of local companies and public actors. MIGHTY is based in two cohesive NUTS-2 regions (North Middle Sweden and Middle Norrland) covering 30 % of Sweden's area. Twinning together the regional S3-strategies for smart specialization with the European strategic goals for digital and green transition, MIGHTY will contribute from both a bottom-up and top-down perspective to make Europe climate neutral by 2050 in accordance with the Paris Agreement by strengthen the resilience and competitiveness of European industry and speed up the uptake and digitalisation within the public sector. Project partners will function as One-Stop-Shop, ensuring wide-spread local presence offering all EDIH-services foreseen in all regions in the spirit that all SMEs should have access to an EDIH within working distance. Cooperation with regional Industrial Networks is key in reach out to manufacturing SME in all regions. MIGHTY is built on long time established and well recognized non-profit-organizations already functioning as regional digital innovation hubs and science parks. This consortium is coordinated by RISE Research Institutes of Sweden and has a strong backing from the regions as well as from the four regional universities. Joining forces in MIGHTY means the consortium will evolve further and faster to better support target groups by leveraging and exchanging services, experience, and know-how of each other and of EDIHs across Europe, supporting the goals in DIGITAL and European Green Deal. | E43: Sweden | F43: Torbjörn Jonsson | G43: Magasinsgatan 10, 82445 Hudiksvall, Sweden | H43: Seal of Excellence | I43: https://www.mighty-edih.se/ | J43: manufacturing and processing, public administration, metal working and industrial production, nmp nonmetallic materials basic processes, construction assembly, environment | K43: circular economy, innovation management, finance, regional development, sme support, sme business development, smart specialisation strategies | L43: logistics, additive manufacturing
A44: =A43+1 -> 43 | B44: 47 | C44: Basque Digital Innovation Hub: EDIH | D44: The BDIH participation in the EDIH initiative and network is essential for the successful growth and transition of the BDIH into a powerhouse of collaborative tech development and adoption at the centre of European competitiveness to achieve a balanced transformation of Basque industry with the use of ever-advanced and secure technologies for future-proofing their competitiveness. The BDIH is a public-private collaboration network made up of a complex ecosystem of universities, technology centres, advanced vocational training centres and business R&D units, which connect their assets/infrastructures, laboratories, equipment, software, and scientific-technological capabilities (people) in the advanced manufacturing environment. Despite its young age, the BDIH is one of the European hubs with the largest number of members at 34, and has over 245 assets available. The BDIH catalogues the knowledge and technology available to its clients in 8 sub-structures called Nodes. These 8 nodes organise the network of assets – a combination of the infrastructure and the associated experts – into discrete services for companies in different fields of technologies and contexts. The implementation of the BDIH-EDIH sits across the three principal pillars of activity which represent the three strands of effective EDIH delivery: Service Provision, EDIH Integration and Strategy and Operations. The BDIH will directly support 360 SMEs and mid-caps in the adoption of digital technology solutions through the direct assessment of their business goals and the pairing of the right technical solutions, assets and expertise to meet theses. Through the already signed MOUs, the membership of existing DIH networks, the BDIH brings the best of Europe to its regional SMEs and will provide cross-DIH services and contribute as an active member of the EIDH with best practices, sector roadshows and support companies in achieving co-investment of over 3 million and 6 million in financing. | E44: Spain | F44: Susana Larrea | G44: Alameda Urquijo 36, 48011 Bilbao Vizcaya, Spain | H44: Seal of Excellence | I44: https://bdih.spri.eus/en/ | J44: manufacturing and processing, energy, health care | K44: prototyping, technological innovation, technology transfer, ecosystem building, finance, sme support | L44: robotics, cybersecurity, additive manufacturing
A45: =A44+1 -> 44 | B45: 48 | C45: HPC & Big Data Processing for a more digital and sustainable Manufacturing | D45: Based on complementarity of roles, a unique specialization on HPC & Big Data Processing for Sustainable Digital Manufacturing and a critical mass of capacity, BIREX++ merges together 15 Italian Champions to provide EU SMEs a full set of innovation and support services to support their twin transition into a more digital and sustainable business world. The Partnerships comprises: Highly-specialized Technologies and Service Providers with a unique critical mass of capability and skills: BIREX, CINECA, University of Bologna, National Inter-University Consortium for Information Technology, ATOS and TIM; Industry Federation and their DIHs with unique access to SME and connection with National Network: Confindustria Emilia-Romagna Ricerca, CNA Emilia-Romagna, PICO (DIH Lega-Coop); International Organization highly specialized in Networking and Ecosystem Management: EIT Manufacturing South, International Foundation Big Data and Artificial Intelligence for Human Develop; Champions in access to Finance and Capitals: Intesa Sanpaolo and Warrant Hub. As a support gateway for industry digitization towards advanced digital technologies, the proposed HUB is built to coordinate key actors on the Italian territory to let them work together in support to the SMEs providing a full set of integrated services, mainly: test-before-invest, training and skills, networking and access to ecosystems, support to find investments. To this end, BIREX++ aims to: (1) coordinate unique technological infrastructures and digital skills on HPC, Big Data and Cloud Computing, Applied-AI and 4.0 enabling technologies; (2) strengthen the capability to engage Manufacturing SMEs in a transformation journey to trigger additional investments; (3) deliver financial advisory services to access finance and capital; (4) establish a full set of networking opportunities and contribute to build a working initial EDIH Network. | E45: Italy | F45: Danilo Mascolo | G45: Via Paolo Nanni costa 14, 40133 Bologna BO, Italy | H45: Seal of Excellence | J45: manufacturing and processing, smart city, telecommunications, consumer products, health care, space, textiles, transport mobility | K45: field trial, innovation management, knowledge transfer, prototyping, sme business development, sme support, technological innovation, technology transfer, circular economy, ecosystem building | L45: additive manufacturing, artificial intelligence decision support, big data, cloud services, cybersecurity, digital twins, high performance computing, internet of things, laserbased manufacturing and materials processing, robotics, virtual reality
A46: =A45+1 -> 45 | B46: 49 | C46: EDIH BOOST Robotics East Netherlands | D46: The East-Netherlands’ economy is predominantly a lively network of SMEs of which many struggle with digital transformation. The EDIH is key to make these SMEs ready for the future digital and green economy and to embed them more prominently in European value chains. EDIH BOOST ROBOTICS EASTNL focuses on Robotics & Sensing in the region’s key sectors Manufacturing, Agrifood and Health. Main objectives are: • To make 350 SMEs in these sectors future proof by increasing their digital maturity with the EDIH’s services • To raise awareness for digital transformation of 1500 SMEs with the EDIH’s services The EDIH will connect, focus and scale the existing ecosystem. It is rooted in DIH BOOST Smart Industry (est. 2016) and builds on fieldlabs, skillslabs and DIH (networks) in the region (DIH-HERO, DIH-RIMA, DIH agROBOfood). Our consortium of 17 partners is dedicated to (1) provide excellent Robotics & Sensing facilities and expertise to SMEs across the EU, (2) connect SMEs, expertise and regional facilities to Europe, and (3) build capacity on digitalisation in the innovation ecosystem. The EDIH will offer new services to SMEs: • Communication and dissemination services to raise the awareness for digital transformation and to collaborate with other Dutch EDIHs; • Digitalisation brokerage to proactively approach SMEs, help them identify digitalisation needs and guide them to the right services of the EDIH or the EU EDIH network; • Test before invest services to open-up test facilities and expertise on i.e. industrial robotics, digital twins, healthcare & agrifood robotics; • Support to find investment for digital transformation to fill gaps in the financial ecosystem; • Skills and Training Modules to improve the ability of professionals to work with digitalisation, robotics and sensing; • International service pilots, networking and match-making services to strengthen SME’s positions in European value chains and to collaborate and create EU corridors between foreign EDIHs. | E46: Netherlands | F46: Bas Ramaker | G46: Markt 11, 6811 CG Arnhem, Netherlands | H46: EDIH | I46: https://european-digital-innovation-hubs.ec.europa.eu/edih-catalogue/edih-boost… | J46: manufacturing and processing, food and beverages, metal working and industrial production, health care | K46: ecosystem building, prototyping, sme support, technology transfer, knowledge transfer | L46: robotics, cyberphysical systems, sensors vision processing systems
A47: =A46+1 -> 46 | B47: 50 | C47: Cybersecurity and AI Hub | France | D47: CYBIAH is an European Digital Innovation Hub (EDIH) based in the Paris Region, dedicated to advancing cybersecurity initiatives with the potential for national and European expansion. Incubated at the heart of Campus Cyber (CCYB), CYBIAH benefits from exclusive access to top-tier cybersecurity experts, enabling the delivery of cutting-edge services to its diverse range of beneficiaries. Recognizing the prohibitive costs associated with cybersecurity solutions, CYBIAH aims to bridge the gap by forming a consortium comprising highly specialized expertise tailored to address the needs of public administrations and SMEs across various sectors. Collaborating with external cyber providers familiar with real-world challenges, CYBIAH strives to achieve two key objectives: Firstly, CYBIAH seeks to make exceptional cybersecurity services accessible to SMEs and public administrations. Secondly, the goal is to foster cybersecurity maturity and innovation within the Paris Region, both among service providers and clients. To support these objectives, CYBIAH has developed customized support packages based on the size, sector, and digital maturity of its beneficiaries. The comprehensive offerings include actions to facilitate digitalization, encompassing training to enhance digital skills and guidance on implementing best practices to achieve and maintain a robust security posture that dissuades potential attackers. The program is structured into four distinct steps – Onboarding, Assessment, Services, and Sustainability. Notably, steps one and two are provided at no cost under specific conditions, while steps three and four are available at preferential rates. CYBIAH's solutions span awareness and anticipation, total protection, as well as detection and reaction. This holistic approach ensures a well-rounded cybersecurity strategy. In summary, CYBIAH's commitment to accessibility, innovation, and tailored support positions it as a key player in advancing cybersecurity resilience across the Paris Region and beyond. | E47: France | F47: Anne-Sophie Colleaux | G47: 5-7 rue bellini, 92800 Puteaux, France | H47: EDIH | I47: https://www.cybiah.eu/ | J47: manufacturing and processing, health care, public administration, travel and tourism, retail, wholesale or distribution | K47: sme support | L47: artificial intelligence decision support, cybersecurity
A48: =A47+1 -> 47 | B48: 51 | C48: European Digital Innovation Hub for North - Central Poland - 1 | E48: Poland | F48: Piotr Józefiak | G48: Wloclawska 167, 87-100 Torun, Poland | H48: Seal of Excellence | I48: https://iotnorthpoland.com/ | J48: manufacturing and processing, health care | K48: sme support | L48: additive manufacturing, robotics, cybersecurity
A49: =A48+1 -> 48 | B49: 52 | C49: Digital Innovation For Lithuanian Industrial Development | D49: Industry need driven European Digital Innovation Hub (EDIH) of Central and Western Lithuania consists of 14 partners operating throughout Lithuania and representing different areas of competence and experience.We are operating in 5 sectors: Manufacturing, Public Sector, Healthcare & Biotechnologies, ICT and Fintech.Our key competences are Artificial Intelligence (AI) and Cybersecurity (CS) in the fields of ​Big data, Automated BMS & WMS, Smart Sensors, ​Robotics, I​oT/IoIT, ​Automation, ​VR/AR, Automatic reporting.​ Aim: a) growth of major digital areas fostered by the EC; b) high level of digital skills and widespread use of digital technologies; c)competitiveness of business models and processes at industries and Public bodies. Mission: To be the one-stop shop that enables effective digitalisation in Manufacturing, Public Administration and emerging sectors. Vision: To raise Lithuania to catch up as a digitalisation leader within Baltic regions. Project goals: a) deliver innovation consulting and support services; b) contribute to global competitiveness of Lithuania innovation ecosystem. Tasks: Increase Lithuania’s competitiveness, productivity, investments in higher value-added products and to promote integration of digital solutions and new technologies. Encourage cooperation between stakeholders at industrial digitalisation/infrastructure development. Help anticipate change and adapt to future needs. Promote digitalisation of the region and society. Strengthen digital skills in public/private sectors. Services: Test Before Invest: customers to obtain reliable expected results for their digitalisation ventures Ecosystem building and networking: operative liaisons through competitive Competence Centers Support to find investment: guide users to simple, efficient and realistic paths for opting to funding schemes Skills and training: practical knowledge at digitalisation, technology and global business Adaptation | E49: Lithuania | F49: Mindaugas Bulota | G49: K.Donelaicio g. 73, 44029 Kaunas, Lithuania | H49: EDIH | I49: https://di4lithuanianid.com/ | J49: manufacturing and processing, public administration, health care, telecommunications, financial | K49: prototyping, ecosystem building, innovation management, technological innovation, sme business development, technology transfer, public sector innovation, smart specialisation strategies, sme support | L49: artificial intelligence decision support, cybersecurity
A50: =A49+1 -> 49 | B50: 53 | C50: DIGITAL EMERGENCY RESPONCE FOR SLOVENIA | D50: DIGI-SI will foster the digital transformation of Small and Medium-sized Enterprises (SMEs), start-ups, scale-ups and Public Administration in four strategic priority areas identified in the forthcoming Slovenian smart specialisation strategy: Agri-food, Health, Tourism and Manufacturing. DIGI-SI has access to crucial infrastructure and highly skilled personnel central to foster the digital revolution in both NUTS2 regions of Slovenia and in Europe. The consortium consisting of seven partners with proven complementary expertise in digital transformation support, will take advantage of the existing resources and provide a single point of contact in all four priority areas of Digital Europe Programme: Artificial Intelligence, High Performance Computing, Cyber Security and Advanced Digital Skills. DIGI-SI also offers technology services within Robotics, Internet of Things, Big data, Blockchain and Augmented / Virtual reality. DIGI-SI will deliver 70 services on entry, basic, and advanced levels and offer collaboration opportunities to Slovenian ICT players to become external digital technology/service providers providing complementary services to local and EU companies through the DIGI-SI online shop enabling matchmaking in demand and supply of digital resources. The modus operandi of DIGI-SI is to offer services and facilitate client journey throughout the circular value chain of defined S5 priority areas. Starting from enabling test-before invest, skills and training, support to find investments, all the while serving as an awareness platform of the benefits and opportunities of the digital age. As a “first-responder” for digital emergencies DIGI-SI has a customer centric approach with an emphasis on timely and efficient service delivery. Apart from physical locations in both NUTS2 regions clients will be able to take advantage of features integrated into the DIGI-SI online shop, such as Academy, Virtual agent, supported by Live agents and Digital emergency hotline. | E50: Slovenia | F50: Muhamed Turkanovic | G50: Slomskov trg 15, 2000 Maribor, Slovenia | H50: EDIH | I50: https://digi-si.eu/ | J50: manufacturing and processing, health care, travel and tourism, agricultural biotechnology and food biotechnology | K50: technology transfer, technological innovation, knowledge transfer, finance, ecosystem building | L50: artificial intelligence decision support, big data, blockchain and distributed ledger technology dlt, cybersecurity, high performance computing, robotics, internet of things, virtual reality
A51: =A50+1 -> 50 | B51: 54 | C51: European Digital Innovation Hub on Manufacturing | D51: The European Digital Innovation Hub DIGITALIS aims to help both traditional SMEs (with the adoption of new digital technologies) and tech savvy SMEs (with building up a competitive advantage in the globalized marketplace). Through our “ecosystem” service we will also bring together both groups of SMEs in order to create a marketplace for digital solutions and let the traditional SMEs learn from their peers. The prime goals are: 1. Increase the uptake of digital technologies on the shopfloor of manufacturing SMEs 2. Increase the level of digital skills on the shopfloor 3. Play an active role in the European network of Digital Innovation Hubs 4. Actively contribute to the European Green Deal goals DIGITALIS thus aims to act as a "one-stop shop" for manufacturing companies that want to digitize their products and processes. Our embedding in the regional as well as the European innovation landscape paves the way to provide the best available service to the SMEs. Although the focus of the EDIH is very clearly on the industry, several concepts, methodologies, and tools may also be relevant to public authorities. Where possible, we will also support these questions The main objectives of DIGITALIS address the core elements of the call for a network of European Digital Innovation Hubs. We will support the digital transformation of EU industrial ecosystems, increase the level of industrial digitalisation, upskill the workforce and reinforce critical digital capacities. DIGITALIS will form the “gateway” to a set of services, technologies and knowledge which are necessary for this digital transition and will play an active role in the European network of EDIHs. We will thus actively support the deployment of digital technologies such as Artificial Intelligence and Cybersecurity (focus of the hub). | E51: Belgium | F51: Ger VAN DEN KERKHOF | G51: Oude diestersebaan 133, 3920 Lommel, Belgium | H51: EDIH | I51: https://digitalis.europeandigitalinnovationhub.com/?page_id=212 | J51: manufacturing and processing, transport mobility | K51: ecosystem building, field trial, finance, innovation management, knowledge transfer, prototyping, sme business development, sme support, technological innovation, technology transfer, vocational training | L51: additive manufacturing, artificial intelligence decision support, cyberphysical systems, cybersecurity, digital twins, high performance computing, internet of things, locationbased applications, micro and nanoelectronics, optoelectronics, photonics, semiconductors and nanotechnology, sensors vision processing systems, simulation engineering and modelling, virtual reality
A52: =A51+1 -> 51 | B52: 55 | C52: EDIH Regiunea Vest Romania | D52: DIGIVEST is the West Region's EDIH located in Timisoara aiming to empower companies uptake digital technologies to boost the regional innovation and competitiveness. The services align around the core objectives to foster digital transformation, support access to finance, leverage international business partnerships, grow digital competences, enable innovation and multi -stakeholder projects. By integrating the EDIH into the regional ecosystem and engaging the existing know-how and network, the EDIH is complementing the emerging ecosystem of West Region striving to offer access to valuable service and to international presence for regional actors into global value chains The value proposition is focusing on the creation of new business opportunities and innovation cooperation. | E52: Romania | F52: Marius Niculae | G52: Lazar Gheorghe 14, 300080 Timisoara, Romania | H52: EDIH | I52: https://www.digivest.ro/ | J52: manufacturing and processing, automotive, transport mobility, nmp nonmetallic materials basic processes, metal working and industrial production, agricultural biotechnology and food biotechnology, food and beverages, consumer products, cultural and creative economy, education, energy, financial, public administration, travel and tourism, aeronautics, health care, smart city | K52: ecosystem building, sme business development, sme support, finance, smart specialisation strategies, technological innovation, innovation management, field trial, regional development, prototyping, circular economy, public sector innovation, vocational training | L52: high performance computing, cybersecurity, internet of things, software architectures, bi tools, additive manufacturing, internet services applications, mobility, simulation engineering and modelling
A53: =A52+1 -> 52 | B53: 56 | C53: Establishment and development of Digital Innovation Hub Mechanika, Bulgaria | D53: The project’s main objective is to establish and develop Digital Innovation Hub Mechanika in town of Peshtera, South Central Region of Bulgaria, which supports SMEs, small-midcaps and public entities in digital transformation through providing services as testing before investing and trainings and consultancy, as well as through providing support to find investment and to find effective collaborations in regional innovation ecosystem. The DIH Mechanika digitalisation objectives are focused on footwear and garment production industry and the related to the shoe industry green and low-carbon technologies. Project’s objectives will be achieved through investments in robotics and 3D technologies for the establishment of digitalisation and industrial design center within the hub, through providing access and services to SMEs, small-midcaps and public entities in development of digital and low-carbon technologies for the footwear and garment industry, as well as through activities for networking and cooperation. The described project’s objectives correspond to the priorities of the call for proposals. The project as well as the programme aims at developing capacities in advance digital skills and best use of technologies for accelerating economic development. Both, the project and the programme aim at accelerating digital transformation in SMEs, small-midcaps and public organisations and both the project and the programme are focusing on development of Industry 4.0 principles through introduction of AI and digital technologies in the manufacturing process. The effect of the project implementation is the increased capacity for digital transformation and innovation activities, including increased innovation potential in the South Central planning region in the field of automation and digitalisation of the footwear and garment industry. | E53: Bulgaria | F53: Gyursel Ingilizov | G53: 1 hristo cikalov str., 4550 Peshtera, Bulgaria | H53: Seal of Excellence | J53: leather, manufacturing and processing | K53: prototyping, innovation management, technological innovation, vocational training, circular economy | L53: robotics, additive manufacturing, simulation engineering and modelling
A54: =A53+1 -> 53 | B54: 57 | C54: Digital Italian Hub for ConstrUction and Built Environment | D54: DIHCUBE aims at establishing the Italian Digital Hub for Construction and the Built Environment. The construction industry is pivotal to the Italian economy (22% of the GDP) and to every citizen’s life, yet it is a sector that suffers from deep backwardness. This is matched by low competitiveness worsened by the recent economic crisis and difficulty in harnessing innovation. The same factors hinder the sustainable transformation of the sector. This is why the Commission has included constructions amongst the 14 priority ecosystems that face the most significant challenges in meeting sustainability goals and in embracing the digital transformation. DIHCUBE will address these issues by bringing together the most advanced research centres and the value chain of the construction industry: SMEs, professionals, suppliers of materials and technology and the public sector. The partners have been chosen to promote a systematic technological shift: they include R&I experts, the Public Sector and specialists in business innovation. Two of them are the most representative organizations of the construction sector; one of them will coordinate the project and will make available its nation-wide network to systematically engage DIHCUBE stakeholders. Given the low level of digitalization in the compartment and the high potential for digital transformation, DIHCUBE services will range from basic digital literacy to advanced pilot coaching for the use of AI and highly specialized consultancy for niche uses. DIHCUBE assistance will be offered across the whole of Italy and will consist of a complete set of services. The Hub will function as a unique access point to the EDIHs network and has already signed an agreement with 6 construction EDIH-candidates. The crisis has deeply hit Italy and the National Recovery Plan has just been deployed. The construction sector, that is central to the Plan, will be able to deliver only if it will undergo a deep green and digital transformation. | E54: Italy | F54: Marco Iuorio | G54: Via guattani 16/18, 00161 Roma RM, Italy | H54: EDIH | I54: https://www.dihcube.eu/ | J54: construction assembly, environment, education, smart city, public administration, manufacturing and processing, real estate | K54: technological innovation, sme support, innovation management, sme business development, vocational training, prototyping, technology transfer, public sector innovation, circular economy, ecosystem building | L54: simulation engineering and modelling, communication network, internet of things, cybersecurity, sensors vision processing systems, cloud services, artificial intelligence decision support, digital twins, gamification, robotics, additive manufacturing, virtual reality
A55: =A54+1 -> 54 | B55: 58 | C55: EDIH Clothing Technology and Textile Hub | D55: European Digital Innovation Hub of Clothing Technology and Textile (CLOTEX-HUB) aims to increase the competitiveness of garment manufacturing products of small and medium-sized enterprises of the Khmelnytskyi region of Ukraine due to the digitisation of clothing manufacturing and the introduction of innovative technologies to ensure the product’s entry into the European market, thus integrating into international chains of creating added value of products and services. CLOTEX-HUB operates within the ecosystem of a sewing cluster factory, providing high-added-value services for experimentation, access to training, technological infrastructures and financial support through a dynamic and interconnected ecosystem, firmly committed to becoming a relevant player in the EDIH network, expanding its collaboration outreach to other European regions. Khmelnytskyi ranks in the top ten in clothing manufacturing in Ukraine, representing over 1000 registered SMEs. The “Development Strategy of Khmelnytskyi Region for 2021-2027” states that the region's smart specialisations are defined as follows: food industry, light industry, mechanical engineering, and metalworking. In the field of light industry in the Khmelnytsky region, where CLOTEX-HUB operates, a smart specialisation is textile and clothing production. On the other hand, innovation capacity and digitalization intensity are still ranked rather low at the European level. EDIH CLOTEX-HUB will contribute to increasing the efficiency level in the sewing industry and machine-building sectors of digital transformation, giving priority to (i) clothing business entities operating in the Khmelnytskyi region of Ukraine and (ii) the implementation of main digital technologies (Advanced Digital Skills, VR/AR technologies, Artificial Intelligent, and Cybersecurity). The consortium consists of four Beneficiaries (Khmelnytskyi National University; NGO Agency for Sustainable Development “ASTAR”; PU “Podillia Fashion Cluster”; NGO “IT CLUSTER OF KHMELNYTSKYI”). | E55: Ukraine | F55: Oksana Zakharkevych | G55: 11, Instytuts’ka str., Khmelnytskyi, Khmel'nyts'ka oblast, 29016, Ukraine | H55: EDIH | I55: https://clotex.khmnu.edu.ua/ | J55: construction assembly, consumer products, cultural and creative economy, education, energy, environment, financial, manufacturing and processing, metal working and industrial production, polymers and plastics, public administration, retail, wholesale or distribution, security, textiles | K55: circular economy, ecosystem building, field trial, finance, innovation management, knowledge transfer, prototyping, public sector innovation, regional development, smart specialisation strategies, sme business development, sme support, technological innovation, technology transfer, vocational training | L55: additive manufacturing, artificial intelligence decision support, chemical engineering plants, products, cybersecurity, digital twins, high performance computing, human computer interaction, internet of things, internet services applications, laserbased manufacturing and materials processing, logistics, new technologies for audiovisual sector media, robotics, sensors vision processing systems, simulation engineering and modelling, virtual reality
A56: =A55+1 -> 55 | B56: 59 | C56: Enabling Digitalisation In the Construction Sector | D56: EDICS project is a collaborative effort of 11 prominent Bulgarian organizations in the construction sector with nationwide coverage and established ecosystems which combine (1) complimentary expertise in digital technologies in the construction sector (2) policy making regarding the development of the construction sector in Bulgaria (3) business networks for clean technologies, innovation and sustainable development (4) technology transfer and access-to-finance capabilities (5) vocational trainings and educational programmes (6) access to Pan-European networks (7) R&D of innovative technologies and greener building materials. The 12th Partner in the Consortium is the newly established NGO “European Digital Innovation Hub” founded by the rest of the project Participants to ensure sustainability of project results. EDICS project main objective is to boost the adoption of advanced digital technologies in the construction in Bulgaria by providing specialized services to SMEs and public sector fitted to their needs and challenges in the green transformation while at the same time acting as a connector to the entire EDIH network and the large pool of digitalization services on a European scale. For doing so, the EDICS project will set up and develop a European Digital Innovation Hub in the Construction Sector (EDIHCS) based in Sofia (Bulgaria), integrating expertise, networks and resources for offering tailor-made services in digitalization of the construction sector. The EDIHCS will act as a one-stop shop for SMEs and public organizations in their journey for digitalization guiding them in the process of assessing their digital maturity, providing the best-fitting services to their specific needs and challenges including test before invest, acceleration and access to finance, and establishing synergies with international networks and platforms for further scale-up of locally-produced innovation. | E56: Bulgaria | F56: Lyubomir Peynovski | G56: ul. Mihail Tenev 6, 1784 Sofia, Bulgaria | H56: EDIH | I56: http://edih-construction.bg | J56: construction assembly | K56: ecosystem building, innovation management, sme support | L56: digital twins, internet of things, locationbased applications, simulation engineering and modelling, artificial intelligence decision support
A57: =A56+1 -> 56 | B57: 60 | C57: A European Digital Innovation Hub for Construction powered by Electronics, Artificial Intelligence & Information and Communication Technologies. | D57: In EU-27, the Construction sector represents 25 million workers, 9,6% GDP, 6,4% of total employment and 5,3 million companies for a total of 101,1 b€ turnover. But the sector faces major challenges for the coming years. With 40% of EU energy consumption, 36% of CO2 emissions and only 1% of renovation rate, the sector must massively invest in the green transition keeping in mind that we spend 90% of our time indoor and 97% of the housing stock is (energy) inefficient. The digitalisation of the sector provides a tremendous lever arm to increase the productivity and respond to this green transition but companies lack information, confidence, skills and access to finance to invest in digital. Studies indicate that digital transformation in the Construction sector can result in productivity gains of 14 to 15 percent and cost reductions of 4 to 6 percent. To respond to economic imperatives and increase the digital maturity of its companies, the construction sector has pulled out all the stops to commit itself to the innovation dynamic driven by Digital Europe and proposes the creation of a European Digital Innovation Hub (EDIH) dedicated to Digital Construction (“CONNECT”) in Wallonia. The project will be based on four pillars (test before invest, skills and competences, innovation eco-system and financial support) and articulated around AI, IoT, robotics and more generally data-driven technologies applied in Construction. As the EC recognised the Construction as a priority industrial ecosystem, the EDIH CONNECT will deeply contribute to this strategy and will specifically tackle the low adoption rate of digital by SMEs and the public administration in Wallonia and in the Construction sector in general. It will also enable Walloon companies to export their know-how within a European dimension, while promoting the digital transformation of a sector that is important for the Walloon economy (13% of added value, 17% of total private employment). | E57: Belgium | F57: Francois Denis | G57: av. Pierre Holoffe 21, 1342 Limelette, Belgium | H57: EDIH | I57: https://www.edih-connect.be | J57: construction assembly, transport sector, manufacturing and processing | K57: ecosystem building, field trial, circular economy | L57: internet of things, artificial intelligence decision support, big data, digital twins
A58: =A57+1 -> 57 | B58: 61 | C58: European Digital Innovation Hub - Energy in the Built Environment | D58: The EDIH-EBE focus is on sectoral coverage on Energy in Buildings and Districts, and as such, positions itself with focus and specialism for digitalisation within sector-coupling between Construction, Energy and ICT. Its main objective is to act as a central access point, a “One-stop-shop” in providing range of services with the ultimate goal to support SMEs and public sector organisations towards successful digital transformation. The ‘hub’ is based on the strong mobilisation of the excellent competences/expertise and infrastructure/facilities already available in Flanders. Customers are supported with knowledge and expertise in (forward looking) digital technologies, trainings to increase competences in skilled work force, networking/info sessions/matchmaking events for improving awareness and bringing together actors of supply and demand in digital solutions, access investments for cost of equipment and software, and testing and experimenting environment to experience benefits leading to higher productivity, better technical performance, new business models and services. Given the EDIH-EBE specialization, the support offered and the target market segments’ economic activity, it has a high potential for direct impact on the goals of the European Green Deal in terms of positive environmental effects and contribution to the reduction of carbon emissions, efficient use of resources, higher productivity and improved technical performance and business cases. Specific objectives are to:▪ Have a specific focus & sectoral coverage on Energy in Buildings and Districts, at level ofindividual buildings, interaction of energy flows between buildings, and interaction with the energy grid. As such, it positions itself with focus and specialism for digitalisation within sector-coupling between Construction, Energy and ICT. ▪ Provide support for several Digital Technologies: Artificial Intelligence (AI), High PerformanceComputing (HPC), Cybersecurity, Internet of Things (IoT), Cloud computing, Building Information Management (BIM), Big Data, Datasets, Data analytics, Simulation/Software, Digital Twin. The overarching motivation is stimulating use of these technologies, withinbusiness/functions to improve products, processes, productivity and services. ▪ Position itself as facilitator for uptake of advanced digital technologies and theiraccelerated use in the construction industry. Embracing digital technologies in the energydomain in the built environment is essential for energy efficient construction and renovation ofbuildings/districts, with increased digitalization in the built environment being seen as muchnecessary step (e.g. ‘Renovation Wave’). Many Flemish companies (and elsewhere in Europe)are lagging in digital skills and are in need of knowledge, skills and experience to increase theirdigital maturity level, making the urgency very high of providing them with necessary support. ▪ Establish fully operational ‘One-Stop-Shop’ in the Region of Flanders (Belgium)incorporating all necessary functionalities for smooth functioning of the EDIH Services.The hub is based on strong mobilisation of the excellent competences/expertise andinfrastructure/facilities already available in Flanders. It is also based on strong mechanisms for networking and matchmaking within its innovation ecosystem as well as collaboration of EDIH-EBE across Europe, namely through benefiting from networking and collaboration within the EU-EDIH- Network and relevant competences and capacities built up in the context of the Digital Europe Programme. | E58: Belgium | F58: Irena Kondratenko | G58: Boeretang 200, 2400 Mol, Belgium | H58: EDIH | I58: https://edih-ebe.eu | J58: construction assembly, energy, smart city, transport mobility | K58: ecosystem building, technological innovation, knowledge transfer, prototyping, vocational training, finance, field trial, public sector innovation, sme support | L58: artificial intelligence decision support, big data, blockchain and distributed ledger technology dlt, cloud services, cybersecurity, digital twins, high performance computing, internet of things, simulation engineering and modelling, virtual reality
A59: =A58+1 -> 58 | B59: 62 | C59: Emilia-Romagna Regional Ecosystem of Digital Innovation | D59: ER2Digit is the European Digital Innovation Hub of the Emilia-Romagna region to promote the improvement of public services and the adoption of innovative digital solutions. ER2Digit supports the digitalization of small and medium enterprises and public bodies through concrete tools, by providing the knowledge, skills and resources to improve their competitiveness in many sectors: health, construction, culture, tourism, monitoring of the territory and sustainability. ER2Digit focuses mainly on artificial intelligence and supercomputing technologies to support the strategic use of data for the enhancement of public services, offering access to top-notch hardware and software infrastructures, while contributing to the assurance of trustworthy data processing. The Hub is built on core competences acquired in 20+ years of innovation policy of the Emilia-Romagna Region, that brought to the creation of an effective innovation ecosystem, made by many public and private actors who invested - and are still investing - in the delivery and adoption of new technologies and innovation across all economic and social sectors. PARTNER A public partnership and an ecosystem to support the Hub ER2Digit is the result of a partnership consisting of: ART-ER, which brings its experience in implementing the innovation practices of the Emilia-Romagna region and in coordinating the local ecosystem and the hub itself. LEPIDA, the main regional public player that supports the digitalization of the public bodies. It is an operational facility of the Emilia-Romagna Regional Authority for the development of telecommunications infrastructure, enabling services and applications, and a driver of the implementation and dissemination of Digital Agenda topics. CINECA, a Consortium composed of 115 Italian universities and public institutions, is the largest computing centre in Italy and one of the main ones worldwide. CINECA hosts and manages LEONARDO, the world’s fourth supercomputer, which provides 20% of Europe’s and 80% of Italy’s computational power. For its activities, ER2Digit also uses the skills and research and experimentation capabilities of the industrial research Laboratories of the Emilia-Romagna High Technology Network. ER2Digit represents an opportunity for digital innovation and for the development of society and the data economy. It is one of the first results of the regional strategy for the creation of the Emilia-Romagna Data Valley. ER2Digit freely provides its audience with FIRST Digital, the web platform that gathers news, events, access to financial and networking opportunities focused on digital transformation. | E59: Italy | F59: Ugo Mencherini/Lucia Mazzoni | G59: Via Piero Gobetti 101, 40129 Bologna BO, Italy | H59: EDIH | J59: construction assembly, cultural and creative economy, energy, health care, life sciences, public administration, transport mobility, travel and tourism | K59: ecosystem building, field trial, finance, innovation management, knowledge transfer, prototyping, public sector innovation, regional development, smart specialisation strategies, sme business development, sme support, technological innovation, technology transfer, vocational training | L59: artificial intelligence decision support, big data, high performance computing, internet of things, locationbased applications
A60: =A59+1 -> 59 | B60: 63 | C60: Digital transformation of Central Croatia and Northern Adriatic through JURK EDIH | D60: Project AI and Gaming EDIH covers geographic area of Central Croatia and Northern Adriatic in Croatia. It is focused on the sector of AI, technologies covered are Game-development (gamification), Blockchain and Internet of Things (IoT). Focus areas will be Agriculture (autonomous drive), Tourism and Hospitality, Health (medical rehabilitation), Wood Industry, Construction, Pharmaceutics, Video-game development, Education. Project consortium makes 8 partners. The lead partner (coordinator) is Regional coordinator of Sisak Moslavina County, other partners are Regional development agency SIMORA with its DIH PISMO, Institute of Physics Zagreb, Faculty of organization and informatics Varaždin, Fastlane LTD, Hashnet LTD, Lipik Development agency/AI Centre Lipik, University College PAR Rijeka with its DIH DigiParc. AI and Gaming EDIH will work with several target groups such as SMEs, start-ups, public sector institutions, citizens. Identity will be built on strong competences of partners - infrastructure, equipment, expertise in business consulting and skills upgrading, knowledge in the field of AI, IoT, Game-development and blockchain, business support. Services of AI and Gaming EDIH are: Test before invest, Skills and trainings, Ecosystem and networking, Support to find investment. 600 SMEs will pass through 36 months of project activities as well as 30 public sector entities. AI and Gaming EDIH has also created strong link with various stakeholders such as chambers, universities, companies, clusters, health institutions, technological parks, agencies and institutes and has networked with number of EDIHs on EU level. AI and Gaming EDIH plans to open discussion about growth and innovation potentials on regional, national and EU level. It will be a contact point in Central Croatia and Northern Adriatic, able to provide all necessary services, infrastructure and equipment to SMEs and public sector, strengthening their capacities, but also creating skilled workforce that will be able to answer to the future needs. | E60: Croatia | F60: Tomislav Plesec | G60: Rimska 28, 44000 Sisak, Croatia | H60: EDIH | I60: https://gaming-edih.hr/ | J60: construction assembly, consumer products, cultural and creative economy, education, health care, metal working and industrial production, paper and wood, public administration, travel and tourism | K60: ecosystem building, field trial, innovation management, knowledge transfer, prototyping, technology transfer, vocational training | L60: gamification, artificial intelligence decision support, blockchain and distributed ledger technology dlt, digital twins, internet of things, virtual reality
A61: =A60+1 -> 60 | B61: 64 | C61: A Norwegian EDIH on Artificial Intelligence | D61: European private and public companies are lagging other regions in exploiting how advanced digital technologies can contribute to better services and more effective/efficient processes and business models. Contributing to this challenge is our dependence on technologies from other regions, and the importance of our collective effort to succeed in becoming greener. The Digital Europe Program will complement other EU Programs by helping private and public companies develop capacities in utilizing High-Performance Computing, Artificial Intelligence, Cybersecurity, Advanced Digital Skills in accelerating the best use of technologies in tackling these challenges. One of the mechanisms deployed through Digital Europe is the European Digital Innovation Hubs. Nemonoor is a Norwegian consortium of eight partners with a long-standing history of collaboration and joint efforts, that has been designated by Norway to become an EDIH. Our belief is that the challenge at hand can only be solved through collaboration among partners that have deep knowledge and experience within all aspects of how private and public companies approach digital, and how they build their capabilities and exploit the opportunities. Our approach is based on two main objectives: support SME/public sector enterprises in Norway with AI Adoption, and ensure EDIH synergies on the European and national levels. Nemonoor partners have a long history of mobilizing private and public companies to act, and to build their capabilities to deploy the technology. With the Nemonoor consortium in place, we have the best means to scale on what we are already doing and release further national and EU funding to activities that contribute to growth and prosperity for European companies and citizens. The application gives a comprehensive description of our capabilities, how we will utilize these capabilities, and how we will engage and assist companies in taking part in the digital transformation journey. | E61: Norway | F61: Eirik Andreassen | G61: Universitetsgata 2, 0164 Oslo, Norway | H61: EDIH | I61: https://www.nemonoor.no/ | J61: construction assembly, education, energy, environment, health care, life sciences, manufacturing and processing, maritime, smart city, transport mobility | K61: ecosystem building, finance, innovation management, knowledge transfer, sme business development, sme support, technological innovation, technology transfer, vocational training | L61: artificial intelligence decision support, big data, cyberphysical systems, cybersecurity, digital twins, high performance computing, human computer interaction, internet of things, mobility, robotics, virtual reality
A62: =A61+1 -> 61 | B62: 65 | C62: nZEB Smart Home DIH | D62: The nZEB Smart Home DIH, coordinated by CERTH's Information Technologies Institute (ITI), was established in early 2017 as the first Hub in Central Macedonia, and has been fully operational ever since. The nZEB Smart Home DIH is an active liaison between research and the markets, acting as a driving force for empowering market-oriented stakeholders with innovative digital solutions. The Smart Home’s technological orientation goes over multiple vertical domains, with special focus on Robotics (commercial or prototype units available for use, integration with devices and sensors, advanced manipulation and control features added), Artificial Intelligence (e.g. intuitive perception and cognition for robotic systems), Cyber physical systems (e.g. embedded systems), Internet of Things (e.g. connected devices, sensors and actuators networks), Simulation and modelling, Big Data, Blockchain, Visual Analytics, and more. One of the unique merits of the DIH is the actual nZEB Smart Home infrastructure. It is a unique Building based on state-of-the-art construction materials (insulation, glass panes, etc.) with "smart" technologies that allow the exploration of various ICT research domains, such as Robotics and Assisted (Tele-) Heath services, or optimized energy efficient building management while simultaneously automating Renewable Energy Sources use. The Smart Home infrastructure is used as a pilot program for validation / testing of new technologies and services provided by the research community. It is equipped with a multi-sensorial network that measures in real-time almost all parameters that consist open challenges for a modern home / workplace (energy, occupancy, health, etc.). In 2019, the IsZEB Cluster emerged from the funded support program "Clusters for promoting innovation in local entrepreneurship." from the Regional Operation Programme Central Macedonia 2014-2020. The Cluster has special focus on the Construction sector, aiming to provide tools and guidelines for the entire lifecycle of a smart zero or positive energy building. Comprised of 16 members, including the leading Greek companies and authorities in the field of Smart Energy Buildings, it operates on the triple helix model, providing R&D services, training & education opportunities, ecosystem development, and innovation management The evolution of the nZEB Smart Home into the IsZEB Cluster marks a strategic progression in fostering innovation and collaboration. Building upon the success and expertise of the nZEB Smart Home initiative, the IsZEB Cluster seamlessly continues its mission, bringing together a diverse array of stakeholders. This transition represents a significant step forward in advancing the economy of smart buildings, facilitating research and development services, ecosystem development, and innovation management for businesses ranging from startups to SMEs and industrial entities. The IsZEB Cluster, maintaining the esteemed attribute of a testbed infrastructure inherited from the nZEB Smart Home, plays a pivotal role in driving collaborative projects and initiatives, creating a dynamic ecosystem for the development of the construction sector. European Initiatives: • Horizon 2020 and Horizon Europe: The IsZEB Cluster participates in various EU-funded R&D projects, aimed at advancing sustainable and innovative solutions in the field of smart and zero-energy buildings (e.g. D2EPC, Response, Accept, EUH4D, metabuilding, InCube, SmartLivingEPC, SUSTAIN Eurocluster, SmartSquare). Accordingly, the nZEB Smart Home participates in various H2020 covering diverse technological domains, from robotics and artificial intelligence to energy-efficient buildings and smart healthcare solutions (Plug-N-Harvest, encompass, Greensoul, ACTIVAGE, GHOST, ACROSSING, INTEGRIDY, VICINITY, DELTA, 3DMicroGrid, eDREAM, DRIMPAC, DIH^2, AI DIH Network, SIT4Energy, AMANDA, AI4EU, DIHNET, BIMERR, MEISTER, PLANET, SMILE, IRIS, AIREGIO, SmartLivingEPC and much more) By participating in those projects, IsZEB Cluster & nZEB Smart Home DIH not only stay at the forefront of technological advancements but also play a crucial role in shaping the EU research landscape. These collaborative endeavours allow them to leverage their expertise, state-of-the-art infrastructure, and multi-sensorial network to contribute with valuable insights and solutions to the various projects. • European Digital Innovation Hubs (EDIHs): The IsZEB Cluster and the nZEB Smart Home participate in the EDIHs, specifically engaging with the Synerginn EDIH and the SmartHealth EDIH. As part of the EDIHs, they operate as a Service Provider, offering a state-of-the-art rapid prototyping and novel technologies demonstration infrastructure, providing a tangible asset for businesses, start-ups, and research institutions to test and showcase emerging technologies. National Initiatives: • Smart Specialization Strategy (RIS3): Since its beginning, the nZEB Smart Home was linked with the RIS3 strategy. The RIS3 supported specialization sectors are correlated to Information & Communication Technologies, Energy Applications/Technologies and Microelectronics – Advanced Materials. The activities interrelate mainly to the investment of creation and dissemination of new knowledge and to the investment in Research & Innovation in the above topics. • Co-Financed by Greece & EU (Central Macedonia Initiatives): IsZEB Cluster was established due to its participation in the programme "Cooperative formations for the promotion of innovation in local entrepreneurship". Its purpose was to promote innovation in local entrepreneurship, foster the sharing of facilities and equipment, and encourage the exchange of knowledge and expertise, networking, dissemination of information and cooperation between companies and other organizations of the cluster. Co-financing fund: European Regional Development Fund (ERDF) | E62: Greece | F62: Dimitrios Tzovaras (Nzeb Smart Home Dih) Zoi Boutopoulou (Iszeb Cluster) | G62: 6th km charilaou – thermi rd, 57001 Thessaloniki, Greece | H62: DIH | I62: https://smarthome.iti.gr/ | J62: construction assembly, energy, health care, security, smart city | K62: ecosystem building, innovation management, knowledge transfer, prototyping, sme support, technological innovation, technology transfer | L62: additive manufacturing, artificial intelligence decision support, big data, blockchain and distributed ledger technology dlt, cyberphysical systems, cybersecurity, gamification, high performance computing, human computer interaction, internet of things, internet services applications, virtual reality, robotics, sensors vision processing systems, simulation engineering and modelling, software architectures
A63: =A62+1 -> 62 | B63: 66 | C63: Mittelstand-Digital Zentrum Kaiserslautern | D63: The Mittelstand-Digital center Kaiserslautern is part of the initiative “Mittelstand-Digital“ by the German Federal Ministry for Economic Affairs and Climate Action (www.mittelstand-digital.de). The Mittelstand-Digital centres, which are located all across Germany, show how digitalisation, innovative networking solutions and Industrie 4.0 applications are used in the daily business practice and they provide active support in the implementation of projects regarding digitalisation. The Mittelstand-Digital Zentrum Kaiserslautern supports companies from Rhineland-Palatinate and beyond. We offer a broad, up-to-date wealth of knowledge and valuable practical experience in the field of Industry 4.0, AI-(Readiness), datadriven businessmodels and sustainable digitalisation. We focus especially on making the findings from many years of research and implementation work available to small and medium-sized enterprises. Funded by the German Federal Ministry for Economic Affairs and Climate Action (Bundesministerium für Wirtschaft und Klima (BMWK)) Keywords: all german SMEs | E63: Germany | F63: Anne Schmallenbach | G63: Trippstadterstraße 122, 67663 Kaiserslautern, Germany | H63: DIH | I63: https://digitalzentrum-kaiserslautern.de/ | J63: construction assembly, consumer products, cultural and creative economy, financial, food and beverages, leather, manufacturing and processing, metal working and industrial production, nmp nonmetallic materials basic processes, personal services, real estate, retail, wholesale or distribution, telecommunications, textiles, transport sector, travel and tourism, paper and wood, polymers and plastics, security | K63: circular economy, innovation management, knowledge transfer, prototyping, sme support, technological innovation, technology transfer | L63: additive manufacturing, artificial intelligence decision support, big data, cyberphysical systems, digital twins, internet of things, sensors vision processing systems
A64: =A63+1 -> 63 | B64: 67 | C64: Mittelstand-Digital Zentrum Darmstadt | D64: The Mittelstand-Digital Zentrum Darmstadt supports small and medium-sized enterprises (SMEs) in their efforts to digizite their business with hands-on-oriented services. All services provided are fully funded by the Federal Ministry for Economic Affairs and Climate Action and create no additionals costs for the recipient. The service includes initial help and orientation for SMEs as well as the support of specific projects. We are also happy to visit companies and partners on site for events and technical consulting. With our online seminars, we offer easily accessible and flexible entry-level formats. We support SMEs that are operating in the manufaturing sector with six key fields of expertise: 1. digital manufaturing 2. product and service development 3. digital work 4. cybersecurity 5. climate-neutral manufacturing 6. artificial intelligence A total of seven partners are pooling their expertise in the Mittelstand-Digital Zentrum Darmstadt: The Institute PTW at TU Darmstadt, the Institutes IAD and PtU and PLCM, the Fraunhofer LBF, the Fraunhofer IGD in Darmstadt and the Chamber of Industry and Commerce in Darmstadt. The Mittelstand-Digital Zentrum Darmstadt is one of 29 centers nationwide in the Mittelstand-Digital network. With Mittelstand-Digital, the Federal Ministry for Economic Affairs and Energy supports digitalization in small and medium-sized enterprises. By working together in the network, we can offer cross-center support and always put SMEs in touch with the right partner if required. | E64: Germany | F64: Nik Weisbrod | G64: Rheinstraße 89, 64295 Darmstadt, Germany | H64: DIH | I64: https://digitalzentrum-darmstadt.de/ | J64: construction assembly, education, energy, manufacturing and processing, metal working and industrial production, smart city | K64: circular economy, ecosystem building, innovation management, knowledge transfer, prototyping, public sector innovation, sme business development, sme support, technology transfer | L64: additive manufacturing, artificial intelligence decision support, big data, cloud services, cyberphysical systems, cybersecurity, digital twins, human computer interaction, internet of things, laserbased manufacturing and materials processing, virtual reality, robotics, sensors vision processing systems, simulation engineering and modelling
A65: =A64+1 -> 64 | B65: 68 | C65: Mittelstand-Digital Zentrum Rostock | D65: The Mittelstand-Digital Zentrum Rostock offers professional support and tailored solutions to small and medium-sized enterprises in Mecklenburg-Western Pomerania, that enable them to benefit from the digital transformation. With our experts and network we want to help companies to turn existing challenges into opportunities. With free events, practical presentations, certified trainings, and individual digital projects, we support SMEs on their journey into a digital company. The Mittelstand-Digital Zentrum Rostock particularly focuses on companies related to the following sectors: healthcare, medical technology, tourism, health tourism, and construction industry. Keywords: AI knowledge transfer, free workshops, e-learning, digitalchecks, demonstrations, networking, keynotes | E65: Germany | F65: Silvia Rydlewicz | G65: Deutsche med platz 1, 18057 Rostock, Germany | H65: DIH | I65: https://www.digitalzentrum-rostock.de | J65: construction assembly, environment, health care, life sciences, travel and tourism, polymers and plastics | K65: knowledge transfer, sme support | L65: artificial intelligence decision support, big data, cybersecurity, industrial biotechnology
A66: =A65+1 -> 65 | B66: 69 | C66: Mittelstand-Digital Zentrum WertNetzWerke | D66: The Mittelstand-Digital Zentrum WertNetzWerke, funded by the Federal Ministry of Economics, supports SMEs free of charge and in a provider-neutral manner in the development and implementation of sustainable and digital business ideas. The Mittelstand-Digital Zentrum WertNetzWerke, funded by the Federal Ministry of Economics, supports SMEs free of charge and in a provider-neutral manner in the development and implementation of sustainable and digital business ideas. | E66: Germany | F66: Tobias Kegler | G66: C/o gs1 germany gmbh, maarweg 133, 50825 Köln, Germany | H66: DIH | I66: https://www.mittelstand-digital-wertnetzwerke.de/ | J66: construction assembly, consumer products, food and beverages, health care, manufacturing and processing, metal working and industrial production, real estate, textiles, transport sector, security, smart city, transport mobility | K66: circular economy, innovation management, knowledge transfer, public sector innovation, regional development, sme business development, sme support, technological innovation, technology transfer | L66: additive manufacturing, artificial intelligence decision support, big data, blockchain and distributed ledger technology dlt, cloud services, communication network, digital twins, gamification, human computer interaction, internet of things, internet services applications, locationbased applications, logistics, virtual reality, robotics, simulation engineering and modelling
A67: =A66+1 -> 66 | B67: 70 | C67: Robocoast EDIH Consortium | D67: Robocoast EDIH supports the manufacturing industry to use digital technology to promote sustainable growth and competitiveness (Industry 4.0). Robocoast EDIH offers one-stop access to EDIH services and networks of European best digital experts, which helps SMEs to become more skilled, innovative, and competitive. Robocoast EDIH has local service nodes and expert resources in the nine regions of Finland, where almost 50% of Finnish manufacturing companies are located. Through EDIH services, Robocoast EDIH combines the needs of the manufacturing industry with the expertise of universities and technology companies. Robocoast EDIH services have been created based on actual needs and long-term cooperation with the manufacturing industry with great results. Robocoast has been Digital Innovation HUB since 2017. Robocoast EDIH has high-level expertise in Cybersecurity and know-how to support companies to apply new digital technologies (AI, Robotics, IoT, 5G and HPC) for developing processes, products, and services. Robocoast EDIH Consortium consists of 15 universities and several RDI laboratories and testbed environments, including over 9 000 digital technology specialists and over 800 Cybersecurity, Robotics, AI, and ICT companies. Based on professionalism, testing, and R&D resources of cybersecurity, The Finnish Information Security Cluster (FISC) strongly recommends the Robocoast EDIH. FISC is an organization established by major Finnish information security companies, and it has nearly 80 members. Robocoast EDIH will be one of the leading centers of cybersecurity in the Digital Europe Program. | E67: Finland | F67: Mikko Puputti | G67: Gallen-Kallelankatu 8, 28100 Pori, Finland | H67: EDIH | I67: https://robocoast.eu/ | J67: construction assembly, defence, education, energy, energy, fuels and petroleum engineering, environment, food and beverages, health care, manufacturing and processing, maritime, metal working and industrial production, nuclear, paper and wood, security, transport mobility, transport sector, travel and tourism | K67: circular economy, ecosystem building, field trial, finance, innovation management, knowledge transfer, prototyping, public sector innovation, regional development, smart specialisation strategies, sme business development, sme support, technological innovation, technology transfer, vocational training | L67: additive manufacturing, artificial intelligence decision support, big data, blockchain and distributed ledger technology dlt, cloud services, communication network, cyberphysical systems, cybersecurity, digital twins, gamification, high performance computing, internet of things, laserbased manufacturing and materials processing, locationbased applications, logistics, mobility, robotics, sensors vision processing systems, simulation engineering and modelling, software architectures, virtual reality
A68: =A67+1 -> 67 | B68: 71 | C68: pro_digital EDIH | D68: What are the goal and target groups of pro_digital? The main goal of pro_digital is to become a one-stop agency for "twin digital and green transformation" in the Brandenburg region. More digitalisation, more sustainability, less resource consumption and CO2 emissions. In the coming months and years, pro_digital will support start-ups, SMEs and midcaps (in short: SMEs) and governmental organisations (public administrations, in short: GOs for Governmental Organisations) in this transformation: higher digital maturity for a more resilient, sustainable, circular, regenerative and green economic growth. pro_digital thus also contributes to the successful structural transformation of Brandenburg. What does pro_digital offer? pro_digital offers knowledge, practical know-how and access to various digital technologies to support businesses and public administrations to increase their performance and competitiveness. pro_digital will provide a portfolio of offers for the target groups in the areas of: Training and information Testing environments to test technologies in real contexts Information on public and private funding for digital transformation | E68: Germany | F68: Tobias Pradel | G68: Hochschulring 1, 15745 Wildau, Germany | H68: EDIH | I68: https://edihprodigital.eu/en | J68: construction assembly, education, manufacturing and processing, metal working and industrial production, public administration | K68: innovation management, knowledge transfer, prototyping, public sector innovation, sme support, technological innovation, technology transfer | L68: additive manufacturing, artificial intelligence decision support, digital twins, high performance computing, internet of things, locationbased applications, robotics, virtual reality, sensors vision processing systems, cybersecurity
A69: =A68+1 -> 68 | B69: 72 | C69: EDUPARK Nonprofit Kft. | D69: EDUPARK Nonprofit Kft. as vocational training provider in the South Great Plain region with practical training centres in Kecskemét and in Szeged, coordinates the Digital Innovation Hub (DIH) in Kecskemét in cooperation with the regional stakeholders as DIH Partnership. DIH Partnership brings together the main players for industrial innovation in Kecskemét with extensive cooperation links to other knowledge centers in Hungary. The technology innovation activities within the DIH Partnership are coordinated by IQ Kecskemét Industrial Research Kft. Our objective is to establish an innovation hub for manufacturing and construction on the basis of IQ Kecskemét which is a physical location for open innovation in architecture and construction industry offering prototyping facilities (CNC machines, 3D scanners and printers), vocational training site and technology development services. The medium term vision of DIH Partnership is to become the acknowledged regional center for entrepreneurial support in digital transformation of the industry which can provide practical advice and support to the SMEs in the region for their activities in digital technology development. It shall lead to the development of an eco-system for innovation that can promote the innovation culture in the central region of Hungary because knowledge based economic development should not be constrained to the capital region of Budapest. The long term objective of DIH Partnership is to play an active role in transnational cooperation for innovation in Central Europe as regional center for industrial digitalization and open innovation in selected industrial sectors and also to foster cooperation and open innovation transnationally on European level. DIH Kecskemét is active player in the support of start-up companies and young individuals that have fresh new ideas having the potential for business by digital solutions. The Digital Welfare Programme (Digitális Jólét Programme) of the Hungarian government have already defined the strategic framework for the advancement of digitalisation in Hungary therefore the local actions of DIH Kecskemét can contribute to the national initiatives (p.e. Modern Vállalkozások Programja, INPUT Program). Education with focus on Digital Skills is a new function that is promoted by the Digital Welfare Programme for benefit of society and the economy in Hungary. Consequently – with the objective to improve the digitalization of companies – the vocational training centre within the DIH Partnership delivers high quality technicians with digital skills for the current and future jobs. It is achieved by dual education schemes that allow SMEs to have a significant role in professional development of younger generation and it shall improve the human capacity of the regional industry within a few years. | E69: Hungary | F69: Tamas Gyulai | G69: Kecskemét, Izsaki ut 8/d, 6000, Hungary | H69: DIH | I69: https://eu-mentor.hu/ | J69: construction assembly, education, manufacturing and processing, metal working and industrial production, polymers and plastics | K69: circular economy, ecosystem building, innovation management, knowledge transfer, prototyping, technological innovation, technology transfer, vocational training | L69: additive manufacturing, high performance computing, internet of things, laserbased manufacturing and materials processing, new technologies for audiovisual sector media, robotics, simulation engineering and modelling
A70: =A69+1 -> 69 | B70: 74 | C70: digihub.li – Ecosystem innovation and growth with a regenerative purpose | D70: OUR PURPOSE «We make Liechtenstein a lighthouse for positive digital transformation that connects humans through trust, transparency, and purpose-driven action.» OUR VISION digihub.li is a European Digital Innovation Hub in the legal form of a Liechtenstein Venture Cooperative (LVC), focused on establishing digital ecosystems for cocreation and collaboration in the token economy.We accelerate digital innovation in Liechtenstein by bringing together SMEs and the public sector in co-creation spaces to jointly tap the potential for viable business models across organizations. Communication on equal terms plays an essential role in this.Building on the forward-looking blockchain legislation in Liechtenstein, we have already invested locally in the necessary Web3 technologies and algorithms for meaningful work to provide immediate relevant offerings to SMEs and the public sector. For us, digitalization and sustainability go hand in hand.We strive for the overall goal to maintain and expand wealth and prosperity as well as attractive workplaces in Liechtenstein by leveraging digital and green transformation. WHAT WE OFFER DIGITAL ECOSYSTEMS Establishing purposeful digital ecosystems, based on the needs of SMEs and the public sector in Liechtenstein Positive digital change enables both quantitative and qualitative growth. In the future, this will be generated primarily through innovation in digital ecosystems. In these, SMEs and the public sector come together to jointly develop thematic solutions for customers. Blockchain technologies are key enablers in this regard, for example in the areas of construction or the Internet of Things (IoT). Step by step, we are bringing SMEs – from solopreneurs to larger manufacturing companies – together with public sector teams in Liechtenstein in our digital collaboration ecosystem to ensure future growth and prosperity for the country. In addition to monthly dialog formats, we are planning larger events such as a Digihub Hack Day and a Digital Innovation Day for the entire country. SKILLS FOR DIGITAL INNOVATION Providing the skills for and of SMEs and public sector employees to thrive in digitalization, and to facilitate the knowledge exchange between the EU and Liechtenstein Our analysis has shown that advanced skills are associated with greater confidence in digital and sustainable transformation. We focus on providing SMEs and public sector teams with access to the best training from the European EDIH network and offer our own training courses focused on meaningful work, communication and blockchain technologies. In addition, we act as a multiplier and disseminate the use of digital competences and resources built under the Digital Europe program. COACHING FOR POSITIVE TRANSITION Practical, task-based coaching to enable trusted, impact-driven collaboration on complex challenges, connecting digital, sustainable and personal transformation We work with leaders and employees to accompany their personal development from «competing against each other» to «co-creating solutions». This shift in the approach to collaboration is a prerequisite for successful work in ecosystems.We invite representatives of SMEs and the public sector in Liechtenstein to participate in our coaching program and open formats such as the «Communication Café», that enable a change of perspective and mind-opening moments in collaboration. INNOVATION NETWORK Hosting innovation spaces for start-ups, SMEs and investors to jointly promote and develop viable digital business models We build and maintain structured long-term relationships with relevant local actors beyond SMEs and the public sector, including impact investors such as foundations, family offices or business angels. Also, we work together with the national authorities, chambers of commerce and industry as well as the banking association and other associations and federations. By matching innovative business models with potential investors, we contribute to the goal of the Liechtenstein government to innovate business models and attract financing for implementation projects. | E70: Liechtenstein | F70: Géraldine D'Atria | G70: Birkenweg 6, 9490 Vaduz, Liechtenstein | H70: EDIH | I70: https://www.digihub.li/ | J70: construction assembly, communityled local development, energy, environment, manufacturing and processing, public administration, transport mobility | K70: circular economy, ecosystem building, innovation management, sme business development, regional development | L70: blockchain and distributed ledger technology dlt, artificial intelligence decision support, internet of things, mobility, virtual reality
A71: =A70+1 -> 70 | B71: 75 | C71: CETMA-Digital Innovation Hub for SMEs | D71: CETMA-DIHSME is the EDIH promoted and managed by CETMA, a non-profit RTO with 30 years of experience in innovation services to SMEs in Southern Italy. In order to strengthen assistance to SMEs with skills, expertise and tools according to a ‘one stop shop’ logic, CETMA involved 13 other partners in the Hub’s service offering. Its activities are strongly focused on the local socio-economic reality (Puglia and Basilicata) where the partners are strongly rooted. CETMA-DIHSME vision is that AI, HPC and CS technologies can bring significant benefits to the development of the Territory, but this requires that anything local actors are involved such as PA and SMEs, even the smallest and even those operating in more traditional sectors. Based on the experience of CETMA and analysis of innovation experts, CETMA-DIHSME starts from the consideration that to foster innovation in small businesses, in addition to "problem solving" services (technology consulting, research, engineering, etc.), it is necessary to support SMEs with "problem setting" services (strategic analysis, business planning, fundraising, supply chain relations, etc.). For this reason, the EDIH CETMA-DIHSME provides an integrated offering of business and strategy-setting services and technological services. We offer services for: awareness building; assistance for strategic setting; testing and development, such as feasibility studies, simulations, development of artificial intelligence applications, testing and optimization of prototypes; testing and development in operating environments. Attention is also dedicated to fundraising support and customised training CETMA-DIHSME aims to trigger synergies with the relevant opportunities offered by regional, national, and European innovation policies and funding and other innovation operators affecting the same territory. It also wants to exploit the great opportunities of the creation of a structured network of EDIH to promote cohesion between European territories to take advantage of social, economic, and environmental benefits. | E71: Italy | F71: Francesca Felline | G71: Strada statale 7 appia km 706+030 snc, 72100 Cittadella della ricerca brindisi BR, Italy | H71: EDIH | I71: https://www.cetma-dihsme.eu | J71: construction assembly, consumer products, cultural and creative economy, health care, manufacturing and processing, maritime, polymers and plastics, public administration, smart city, transport mobility, aeronautics, agricultural biotechnology and food biotechnology, automotive, communityled local development, defence, education, energy, environment, leather, life sciences, metal working and industrial production, nmp nonmetallic materials basic processes, nuclear, paper and wood, retail, wholesale or distribution, space, telecommunications, textiles, transport sector | K71: circular economy, innovation management, knowledge transfer, public sector innovation, regional development, sme support, technological innovation, technology transfer, ecosystem building, field trial, finance, prototyping, smart specialisation strategies, sme business development | L71: artificial intelligence decision support, big data, cybersecurity, gamification, high performance computing, internet of things, internet services applications, logistics, mobility, new technologies for audiovisual sector media, robotics, sensors vision processing systems, simulation engineering and modelling, virtual reality, cloud services, communication network, digital twins, human computer interaction, laserbased manufacturing and materials processing
... A75: =A74+1 -> 74 | B75: 79 | C75: Digital Innovation Unit | D75: The Digital Innovation Unit (DIU) is a leading-edge hub in Albania, fostering digital transformation by supporting entrepreneurs, startups, and SMEs. DIU provides a broad spectrum of digitalization services, technology training, networking opportunities, and a dedicated space to test innovations. The unit focuses on key digital domains including Artificial Intelligence, Cybersecurity, Programming, Data Science, Virtual Reality, Blockchain, Animation, and Robotics, ensuring companies increase efficiency, optimize resources, and enhance profitability. | E75: Albania | F75: Ami Çarçani | G75: DESHMORET E 4 SHKURTIT, 1001, Tirana, Albania | H75: EDIH | I75: https://meki.gov.al/ | J75: education, financial, manufacturing and processing, public administration, retail, wholesale or distribution, smart city, transport mobility, health care | K75: sme support, technological innovation, technology transfer, vocational training, prototyping, ecosystem building, innovation management | L75: artificial intelligence decision support, cybersecurity, blockchain and distributed ledger technology dlt, cloud services, internet of things, software architectures, virtual reality, robotics
A76: =A75+1 -> 75 | B76: 80 | C76: Cybersecurity and digital competencies | D76: DigitalTech EDIH is the reference Hub in Hungary to support start-ups, SMEs, mid-caps and public sector entities in their digital transformation focusing on key pillars of European priorities. DigitalTech EDIH relies on its ecosystem to address major issues of cybersecurity and digital competencies including blockchain technology, education technology and digital finance. Based on its partner’s expertise DigitalTech EDIH will deliver expertise to its clients through our service catalogue, which covers four components including skills and training, test before invest, innovation ecosystem and networking and support to find investments, along with other business development services and technology-related advisory. DigitalTech EDIH will also have the opportunity to offer its services to the other Hungarian EDIHs, regional EDIHs as well as to the pan-European network of EDIHs, in line with the European Regional Innovation Strategy. DigitalTech EDIH is part of the European Corridor of Cybersecurity EDIHs (ECCE), a network of EDIHs supported by the European Cyber Security Organisation (ECSO) and specifically dedicated to cybersecurity in order to enhance our collective actions. DigitalTech EDIH will act as a catalyst for these ecosystems and will contribute to their digital transformation, thus strengthening its resilience and ensuring its sustainability for Hungary and the region and making contributions to realising the ambitions of building and sustaining a competitive European digital workforce for the Digital Decade and beyond. | E76: Hungary | F76: Tuan Trinh | G76: Budapest, Bogdanfy utca 10/a., 1117, Hungary | H76: EDIH | J76: education, financial, public administration | K76: knowledge transfer, sme business development, vocational training, public sector innovation | L76: blockchain and distributed ledger technology dlt, cybersecurity, cyberphysical systems
A77: =A76+1 -> 76 | B77: 81 | C77: SEEU TechPark EDIH | D77: SEEU Tech Park aims at providing conditions to stimulate the creation of new start-up companies, make a synergy between the companies and encourage the growth of the existing small and medium sized enterprises (SMEs), resulting in generating new job opportunities. SEEU Tech Park’s mission is the development of start- up knowledge based companies at SEEU, designed to create and foster an entrepreneurial culture among faculty, researchers, and students of SEEU, as well as commercialization of scientific and technological knowledge. Its vision is to create an environment within the University that will forge closer ties and endure links between academia and the industry in order to convert knowledge and expertise into Action, Production and Investment. | E77: North Macedonia | F77: Blerina Zendeli | G77: Ilindenska, no. 335, 1200 Tetovo, North Macedonia | H77: Seal of Excellence | I77: https://www.seeu.edu.mk/ | J77: education, environment, manufacturing and processing, public administration, security, smart city, transport mobility | K77: circular economy, innovation management, knowledge transfer, prototyping, regional development, smart specialisation strategies, sme business development, sme support, technological innovation, technology transfer, vocational training | L77: artificial intelligence decision support, bi tools, big data, communication network, cyberphysical systems, cybersecurity, digital twins, human computer interaction, internet of things, mobility, software architectures, virtual reality
A78: =A77+1 -> 77 | B78: 82 | C78: FactoryxChange | D78: Manufacturing Digital Transformation The FactoryXChange (FXC), European Digital Innovation Hub (EDIH) will enable Industry 5.0 factories to integrate ecological, digital, and societal solutions into their core business models. FxC is best positioned to support the ambitions of the Digital Europe Programme 2021-2027 to ensure that Europe embraces the digital transformation of the economy and society and brings its benefits to businesses and citizens. FxC will extend digital competencies (high performance computing, artificial intelligence, and cybersecurity) and advanced skills in digital technologies to stakeholders, particularly Small and Medium-sized Enterprises (SMEs), contributing to Europe’s strategic autonomy, and accelerating deployment and best use in areas of public interest and the private sector. FxC will operationalise Ireland’s Smart Specialisation Strategy priority areas of Manufacturing (Industry5.0) and where industry overlaps with ICT, energy, health, and Key Digital Technologies considering the ethical, security, data, and equality challenges. The overall objective of FxC is to realise the EDIH as a one-stop-shop with impact. Operationalising an Industry 5.0 EDIH that responds to customer needs in a fast flexible manner, removing financial and operational barriers, by disrupting the way we make things through digital innovations and knowledge exchange. No matter where you are on the island of Ireland you are never more than a 90-minute journey (or a few clicks online) from a trusted broker (Digital Strategist) your connection to the digital capacities offered through FxC. FXC integrates the world-class technical competencies of ICHEC (the National Centre for high performance computing) and INSIGHT (the National Centre for data analytics) to realise a state-of-the-art offering for Enterprise, augmented by the services of at three additional Digital Innovation Hubs in advanced digital capacity and skills, available through Irish Manufacturing Research (IMR), Technological University of the Shannon (TUS) and Data Value Hub (DVH) with KPMG Future Analytics adding to the digital solutions and digital interoperability, with a particular focus on Public Organisations. | E78: Ireland | F78: Irish Manufacturing Research | G78: National Science Park, Mullingar, Co. Westmeath, N91 TX80, Ireland | H78: EDIH | I78: https://www.factoryxchange.ie/ | J78: education, financial, manufacturing and processing, metal working and industrial production | K78: circular economy, sme support, sme business development, knowledge transfer, finance, innovation management, technology transfer, technological innovation | L78: data, additive manufacturing, artificial intelligence decision support, big data, internet of things, internet services applications, robotics, simulation engineering and modelling, cybersecurity
A79: =A78+1 -> 78 | B79: 83 | C79: Thessaloniki Innovation Ecosystem | D79: OK!Thess provides entrepreneurial training to start-ups and SMEs in various topics, giving access to methodological tools needed. It runs training programs in the fields of Financial Management and Fundraising methods, Product Development, Market and Competition, Business Model Discovery and Company’s development Vertical Expertise. We provide one-to-one coaching to start-ups and SMEs exploiting its team expertise as well as industry experts from its network of mentors. We organize and participate in networking events engaging its network of investors and big corporates that have already participated in the events organised by the accelerator. | E79: Greece | F79: Antonios Ilias | G79: 2 komotinis street, 54655 Thessaloniki, Greece | H79: DIH | I79: https://okthess.gr/ | J79: education, life sciences, personal services | K79: ecosystem building, innovation management, knowledge transfer, public sector innovation, sme business development, sme support | L79: communication network
A80: =A79+1 -> 79 | B80: 84 | C80: Mittelstand-Digital Zentrum Hannover | D80: The Mittelstand-Digital Zentrum Hannover offers company meetings, training and support for digitalization and AI projects in companies. Thanks to funding from the Federal Ministry for Economic Affairs and Climate Action, the center's services are free of charge. The aim of the center is to enable companies to independently create the conditions to drive forward digitalization measures and use artificial intelligence. | E80: Germany | F80: Gerold Kuiper | G80: Osteriede 6, 30827 Garbsen, Germany | H80: DIH | I80: https://digitalzentrum-hannover.de/ | J80: education | K80: innovation management, knowledge transfer, prototyping, public sector innovation, regional development, smart specialisation strategies, sme support, technological innovation, technology transfer | L80: artificial intelligence decision support, big data, cybersecurity, digital twins, internet of things, virtual reality
A81: =A80+1 -> 80 | B81: 85 | C81: Mittelstand-Digital Zentrum Schleswig-Holstein | D81: Das Mittelstand-Digital Zentrum Schleswig-Holstein ist ein vom BMWK gefördertes Projekt, um KMU bei der Digitalisierung zu unterstützen. Im Rahmen dessen befassen wir uns hauptsächlich mit den Themen KI, IoT, Sensorik, vernetzte Produktion, Digitaler Zwilling, AR/VR sowie Changemanagement und Geschäftsmodelle. In diesem Spektrum bieten wir kostenlose Informationsveranstaltungen, Sprechstunden, Workshops oder Projekte an. __________ The Mittelstand-Digital Zentrum Schleswig-Holstein is a project funded by the BMWK to support SMEs with digitalization. Within this framework, we mainly deal with the topics of AI, IoT, sensor technology, networked production, digital twin, AR/VR as well as change management and business models. Within this spectrum, we offer free information events, consultation hours, workshops and projects. | E81: Germany | F81: Regine Schlicht | G81: Luisenstraße 26, 24149 Kiel, Germany | H81: DIH | I81: https://www.digitalzentrum-sh.de/ | J81: education, health care, life sciences, manufacturing and processing, metal working and industrial production, regulation | K81: innovation management, knowledge transfer, prototyping, regional development, sme business development, sme support, technological innovation, technology transfer | L81: additive manufacturing, artificial intelligence decision support, big data, cyberphysical systems, digital twins, high performance computing, human computer interaction, internet of things, virtual reality, robotics, sensors vision processing systems, simulation engineering and modelling
